Workbook

Sheet Garde
B8: HCTech SARL
B9: Récupération des vapeurs d'essence en station-service
B11: Business Plan & Dossier de financement — Leasing
B12: Modèle Revenue Share 60 / 40 · Machines financées en leasing · Horizon 7 ans
B14: Points clés
B15: Parc cible (An 7) | C15: ='Synthèse'!C5
B16: Résultat net cumulé (7 ans) | C16: ='Synthèse'!C8
B17: Couverture du loyer / machine | C17: ='Synthèse'!C13
B18: DSCR minimum | C18: ='Synthèse'!C14
B19: Trésorerie minimale | C19: ='Synthèse'!C9
B20: Dette bancaire | C20: =0
B23: Société à Responsabilité Limitée — RNE : 1953633L — 01 av. Hedi Khefacha, 2080 Ariana
B25: Document confidentiel — réservé aux établissements de leasing et partenaires financiers identifiés.
B26: Préparé par Mohamed Ridha Belajouza, consultant et conseiller stratégique.

Sheet Hypothèses
B1: Hypothèses du modèle
B2: Toutes les cellules bleues sont modifiables — le classeur entier se recalcule automatiquement.
B4: PARAMÈTRES MACHINE & LEASING
B5: Taux de change USD / TND | C5: 2.95 | E5: Cours de référence
B6: Prix machine (départ usine) | C6: 18000 | D6: USD | E6: Fournisseur GEKO (Corée)
B7: Frais d'import | C7: 0.025 | D7: % | E7: Droits + transit
B8: Installation | C8: 3500 | D8: DT | E8: Prestataire local
B9: Coût machine tout compris (HT) | C9: =C6*C5*(1+C7)+C8 | D9: DT | E9: Base de l'opération de leasing
B10: Taux de leasing machine | C10: 0.12 | D10: %/an | E10: Marché tunisien (plafond usure 16,28 %)
B11: Durée du leasing machine | C11: 5 | D11: ans | E11: Règle Tunisie : leasing équipement 5 ans
B12: Mensualité leasing / machine | C12: =C9*(C10/12)/(1-(1+C10/12)^(-C11*12)) | D12: DT | E12: Annuité constante
B13: Loyer leasing annuel / machine | C13: =C12*12 | D13: DT/an | E13: Pendant 5 ans, puis 0
B14: Maintenance + internet / machine | C14: 120 | D14: DT/mois | E14: OPEX par machine
B16: REVENUS PAR MACHINE
B17: Volume station cible | C17: 12000 | D17: L/jour | E17: Stations ≥ 12 000 L/j (~60 % du parc)
B18: Taux de récupération | C18: 5 | D18: /1000 | E18: Hypothèse médiane (fourchette 3–7/1000)
B19: Essence récupérée / machine | C19: =C17*C18/1000 | D19: L/jour | E19: volume × taux
B20: Prix de l'essence (An 1) | C20: 2.525 | D20: DT/L | E20: Prix à la pompe
B21: Hausse du prix de l'essence | C21: 0.045 | D21: %/an | E21: CAGR réel 2016–2026
B22: Part HCTECH (revenue share) | C22: 0.6 | D22: % | E22: Partage 60 / 40
B23: Part station | C23: =1-C22 | D23: % | E23: Station : 0 investissement
B25: DÉPLOIEMENT DU PARC
B26: Machines par vague | C26: 14 | D26: mach. | E26: Une vague tous les 6 mois
B27: Intervalle entre vagues | C27: 6 | D27: mois
B28: Mois du 1er déploiement | C28: 3 | D28: mois
B29: Nombre de vagues | C29: 14 | D29: vagues
B30: Horizon du plan | C30: 84 | D30: mois | E30: 7 ans
B31: Parc final | C31: =C26*C29 | D31: mach. | E31: Cible à l'An 7
B33: CHARGES DE STRUCTURE
B34: Nombre de gérants / fondateurs | C34: 2 | D34: pers. | E34: Ali + Lamine
B35: Salaire fondateur (An 1) | C35: 2000 | D35: DT/mois
B36: Croissance salaire fondateur | C36: 0.5 | D36: %/an | E36: Plafonnée
B37: Plafond salaire fondateur | C37: 6000 | D37: DT/mois
B38: Salaire technicien (An 1) | C38: 1200 | D38: DT/mois
B39: Croissance salaire technicien | C39: 0.07 | D39: %/an
B40: Machines par technicien | C40: 48 | D40: mach. | E40: Capacité d'un technicien
B41: Charges patronales | C41: 0.21 | D41: % | E41: CNSS + TFP + FOPROLOS
B42: Loyer bureau (An 1) | C42: 1200 | D42: DT/mois
B43: Croissance loyer bureau | C43: 0.06 | D43: %/an
B44: Frais généraux (An 1) | C44: 2000 | D44: DT/mois | E44: Admin, déplacements, divers
B45: Croissance frais généraux | C45: 0.06 | D45: %/an
B47: VÉHICULE UTILITAIRE (leasing)
B48: Prix du véhicule | C48: 70000 | D48: DT | E48: Intervention / maintenance
B49: Taux de leasing véhicule | C49: 0.12 | D49: %/an
B50: Durée du leasing véhicule | C50: 60 | D50: mois | E50: 5 ans
B51: Mensualité véhicule | C51: =C48*(C49/12)/(1-(1+C49/12)^(-C50)) | D51: DT
B53: FISCALITÉ & CAPITAL
B54: Impôt sur les sociétés (IS + CSS) | C54: 0.28 | D54: % | E54: IS 25 % + CSS 3 %
B55: Capital social | C55: 300000 | D55: DT | E55: Apporté à 100 % par Nessim Mami
B56: Payout dividendes | C56: 0.7 | D56: % | E56: 70 % distribué, 30 % en réserve
B57: Prime de risque investisseur | C57: 0.2 | D57: % | E57: Sur récupération prioritaire
B58: Récupération prioritaire Nessim | C58: =C55*(1+C57) | D58: DT | E58: Capital + prime (= 360 000)
B60: RÉPARTITION DU CAPITAL
B61: Nessim Mami (investisseur) | C61: 0.45 | D61: % | E61: Apporte 100 % du capital
B62: Ali Ben Hamoud (Directeur Technique) | C62: 0.25 | D62: % | E62: Apport industrie
B63: Mohamed Lamine Belajouza (CEO) | C63: 0.25 | D63: % | E63: Apport industrie
B64: Nazeh Ben Ammar (conseiller de Nessim) | C64: 0.05 | D64: % | E64: Apport réseau institutionnel
B66: Cellules bleues = saisie libre. Cellules grisées = calculées (ne pas modifier).

Sheet Économie machine
B1: Économie d'une machine
B2: Le cœur du modèle : chaque machine s'autofinance et dégage une marge nette.
B4: INVESTISSEMENT & FINANCEMENT
B5: Coût machine tout compris (HT) | C5: ='Hypothèses'!$C$9
B6: Financement | E6: Leasing 100 % (0 cash mobilisé par HCTECH)
B7: Loyer de leasing / mois | C7: ='Hypothèses'!$C$12
B8: Loyer de leasing / an (pendant 5 ans) | C8: ='Hypothèses'!$C$13
B10: REVENUS (scénario réaliste 5/1000)
B11: Essence récupérée / an | C11: ='Hypothèses'!$C$19*365
B12: Valeur brute récupérée / an | C12: ='Hypothèses'!$C$19*365*'Hypothèses'!$C$20
B13: Part HCTECH (60 %) | C13: ='Hypothèses'!$C$19*365*'Hypothèses'!$C$20*'Hypothèses'!$C$22
B14: Part station (40 %) | C14: ='Hypothèses'!$C$19*365*'Hypothèses'!$C$20*'Hypothèses'!$C$23
B16: MARGE PAR MACHINE
B17: (−) Loyer leasing / an | C17: =-'Hypothèses'!$C$13
B18: (−) Maintenance + internet / an | C18: =-'Hypothèses'!$C$14*12
B19: Marge nette PENDANT le leasing (5 ans) | C19: ='Hypothèses'!$C$19*365*'Hypothèses'!$C$20*'Hypothèses'!$C$22-'Hypothèses'!$C$13-'Hypothèses'!$C$14*12
B20: Marge nette APRÈS payoff (An 6-7, loyer = 0) | C20: ='Hypothèses'!$C$19*365*'Hypothèses'!$C$20*'Hypothèses'!$C$22-'Hypothèses'!$C$14*12
B21: Couverture du loyer par la part HCTECH | C21: ='Hypothèses'!$C$19*365*'Hypothèses'!$C$20*'Hypothèses'!$C$22/'Hypothèses'!$C$13

Sheet État de résultat
B1: État de résultat prévisionnel
B2: Présentation normée (Système Comptable des Entreprises — Tunisie). En DT — recalcul automatique.
C4: An 1 | D4: An 2 | E4: An 3 | F4: An 4 | G4: An 5 | H4: An 6 | I4: An 7 | J4: Total 7 ans
B5: Parc de machines en exploitation (fin d'année) — pour mémoire | C5: ='Calcul'!$D$13 | D5: ='Calcul'!$D$25 | E5: ='Calcul'!$D$37 | F5: ='Calcul'!$D$49 | G5: ='Calcul'!$D$61 | H5: ='Calcul'!$D$73 | I5: ='Calcul'!$D$85
B6: PRODUITS D'EXPLOITATION
B7: Revenus (revenue share — part HCTECH 60 %) | C7: =SUMIF('Calcul'!$B$2:$B$85,1,'Calcul'!$H$2:$H$85) | D7: =SUMIF('Calcul'!$B$2:$B$85,2,'Calcul'!$H$2:$H$85) | E7: =SUMIF('Calcul'!$B$2:$B$85,3,'Calcul'!$H$2:$H$85) | F7: =SUMIF('Calcul'!$B$2:$B$85,4,'Calcul'!$H$2:$H$85) | G7: =SUMIF('Calcul'!$B$2:$B$85,5,'Calcul'!$H$2:$H$85) | H7: =SUMIF('Calcul'!$B$2:$B$85,6,'Calcul'!$H$2:$H$85) | I7: =SUMIF('Calcul'!$B$2:$B$85,7,'Calcul'!$H$2:$H$85) | J7: =SUM(C7:I7)
B8: CHARGES D'EXPLOITATION
B9: Achats & charges externes — maintenance machines | C9: =-SUMIF('Calcul'!$B$2:$B$85,1,'Calcul'!$I$2:$I$85) | D9: =-SUMIF('Calcul'!$B$2:$B$85,2,'Calcul'!$I$2:$I$85) | E9: =-SUMIF('Calcul'!$B$2:$B$85,3,'Calcul'!$I$2:$I$85) | F9: =-SUMIF('Calcul'!$B$2:$B$85,4,'Calcul'!$I$2:$I$85) | G9: =-SUMIF('Calcul'!$B$2:$B$85,5,'Calcul'!$I$2:$I$85) | H9: =-SUMIF('Calcul'!$B$2:$B$85,6,'Calcul'!$I$2:$I$85) | I9: =-SUMIF('Calcul'!$B$2:$B$85,7,'Calcul'!$I$2:$I$85) | J9: =SUM(C9:I9)
B10: Charges de leasing — machines | C10: =-SUMIF('Calcul'!$B$2:$B$85,1,'Calcul'!$J$2:$J$85) | D10: =-SUMIF('Calcul'!$B$2:$B$85,2,'Calcul'!$J$2:$J$85) | E10: =-SUMIF('Calcul'!$B$2:$B$85,3,'Calcul'!$J$2:$J$85) | F10: =-SUMIF('Calcul'!$B$2:$B$85,4,'Calcul'!$J$2:$J$85) | G10: =-SUMIF('Calcul'!$B$2:$B$85,5,'Calcul'!$J$2:$J$85) | H10: =-SUMIF('Calcul'!$B$2:$B$85,6,'Calcul'!$J$2:$J$85) | I10: =-SUMIF('Calcul'!$B$2:$B$85,7,'Calcul'!$J$2:$J$85) | J10: =SUM(C10:I10)
B11: Charges de leasing — véhicule | C11: =-SUMIF('Calcul'!$B$2:$B$85,1,'Calcul'!$Q$2:$Q$85) | D11: =-SUMIF('Calcul'!$B$2:$B$85,2,'Calcul'!$Q$2:$Q$85) | E11: =-SUMIF('Calcul'!$B$2:$B$85,3,'Calcul'!$Q$2:$Q$85) | F11: =-SUMIF('Calcul'!$B$2:$B$85,4,'Calcul'!$Q$2:$Q$85) | G11: =-SUMIF('Calcul'!$B$2:$B$85,5,'Calcul'!$Q$2:$Q$85) | H11: =-SUMIF('Calcul'!$B$2:$B$85,6,'Calcul'!$Q$2:$Q$85) | I11: =-SUMIF('Calcul'!$B$2:$B$85,7,'Calcul'!$Q$2:$Q$85) | J11: =SUM(C11:I11)
B12: Charges de personnel | C12: =-SUMIF('Calcul'!$B$2:$B$85,1,'Calcul'!$N$2:$N$85) | D12: =-SUMIF('Calcul'!$B$2:$B$85,2,'Calcul'!$N$2:$N$85) | E12: =-SUMIF('Calcul'!$B$2:$B$85,3,'Calcul'!$N$2:$N$85) | F12: =-SUMIF('Calcul'!$B$2:$B$85,4,'Calcul'!$N$2:$N$85) | G12: =-SUMIF('Calcul'!$B$2:$B$85,5,'Calcul'!$N$2:$N$85) | H12: =-SUMIF('Calcul'!$B$2:$B$85,6,'Calcul'!$N$2:$N$85) | I12: =-SUMIF('Calcul'!$B$2:$B$85,7,'Calcul'!$N$2:$N$85) | J12: =SUM(C12:I12)
B13: Loyer & charges locatives (bureau) | C13: =-SUMIF('Calcul'!$B$2:$B$85,1,'Calcul'!$O$2:$O$85) | D13: =-SUMIF('Calcul'!$B$2:$B$85,2,'Calcul'!$O$2:$O$85) | E13: =-SUMIF('Calcul'!$B$2:$B$85,3,'Calcul'!$O$2:$O$85) | F13: =-SUMIF('Calcul'!$B$2:$B$85,4,'Calcul'!$O$2:$O$85) | G13: =-SUMIF('Calcul'!$B$2:$B$85,5,'Calcul'!$O$2:$O$85) | H13: =-SUMIF('Calcul'!$B$2:$B$85,6,'Calcul'!$O$2:$O$85) | I13: =-SUMIF('Calcul'!$B$2:$B$85,7,'Calcul'!$O$2:$O$85) | J13: =SUM(C13:I13)
B14: Autres charges d'exploitation | C14: =-SUMIF('Calcul'!$B$2:$B$85,1,'Calcul'!$P$2:$P$85) | D14: =-SUMIF('Calcul'!$B$2:$B$85,2,'Calcul'!$P$2:$P$85) | E14: =-SUMIF('Calcul'!$B$2:$B$85,3,'Calcul'!$P$2:$P$85) | F14: =-SUMIF('Calcul'!$B$2:$B$85,4,'Calcul'!$P$2:$P$85) | G14: =-SUMIF('Calcul'!$B$2:$B$85,5,'Calcul'!$P$2:$P$85) | H14: =-SUMIF('Calcul'!$B$2:$B$85,6,'Calcul'!$P$2:$P$85) | I14: =-SUMIF('Calcul'!$B$2:$B$85,7,'Calcul'!$P$2:$P$85) | J14: =SUM(C14:I14)
B15: Total des charges d'exploitation | C15: =-(SUMIF('Calcul'!$B$2:$B$85,1,'Calcul'!$I$2:$I$85)+SUMIF('Calcul'!$B$2:$B$85,1,'Calcul'!$J$2:$J$85)+SUMIF('Calcul'!$B$2:$B$85,1,'Calcul'!$Q$2:$Q$85)+SUMIF('Calcul'!$B$2:$B$85,1,'Calcul'!$N$2:$N$85)+SUMIF('Calcul'!$B$2:$B$85,1,'Calcul'!$O$2:$O$85)+SUMIF('Calcul'!$B$2:$B$85,1,'Calcul'!$P$2:$P$85)) | D15: =-(SUMIF('Calcul'!$B$2:$B$85,2,'Calcul'!$I$2:$I$85)+SUMIF('Calcul'!$B$2:$B$85,2,'Calcul'!$J$2:$J$85)+SUMIF('Calcul'!$B$2:$B$85,2,'Calcul'!$Q$2:$Q$85)+SUMIF('Calcul'!$B$2:$B$85,2,'Calcul'!$N$2:$N$85)+SUMIF('Calcul'!$B$2:$B$85,2,'Calcul'!$O$2:$O$85)+SUMIF('Calcul'!$B$2:$B$85,2,'Calcul'!$P$2:$P$85)) | E15: =-(SUMIF('Calcul'!$B$2:$B$85,3,'Calcul'!$I$2:$I$85)+SUMIF('Calcul'!$B$2:$B$85,3,'Calcul'!$J$2:$J$85)+SUMIF('Calcul'!$B$2:$B$85,3,'Calcul'!$Q$2:$Q$85)+SUMIF('Calcul'!$B$2:$B$85,3,'Calcul'!$N$2:$N$85)+SUMIF('Calcul'!$B$2:$B$85,3,'Calcul'!$O$2:$O$85)+SUMIF('Calcul'!$B$2:$B$85,3,'Calcul'!$P$2:$P$85)) | F15: =-(SUMIF('Calcul'!$B$2:$B$85,4,'Calcul'!$I$2:$I$85)+SUMIF('Calcul'!$B$2:$B$85,4,'Calcul'!$J$2:$J$85)+SUMIF('Calcul'!$B$2:$B$85,4,'Calcul'!$Q$2:$Q$85)+SUMIF('Calcul'!$B$2:$B$85,4,'Calcul'!$N$2:$N$85)+SUMIF('Calcul'!$B$2:$B$85,4,'Calcul'!$O$2:$O$85)+SUMIF('Calcul'!$B$2:$B$85,4,'Calcul'!$P$2:$P$85)) | G15: =-(SUMIF('Calcul'!$B$2:$B$85,5,'Calcul'!$I$2:$I$85)+SUMIF('Calcul'!$B$2:$B$85,5,'Calcul'!$J$2:$J$85)+SUMIF('Calcul'!$B$2:$B$85,5,'Calcul'!$Q$2:$Q$85)+SUMIF('Calcul'!$B$2:$B$85,5,'Calcul'!$N$2:$N$85)+SUMIF('Calcul'!$B$2:$B$85,5,'Calcul'!$O$2:$O$85)+SUMIF('Calcul'!$B$2:$B$85,5,'Calcul'!$P$2:$P$85)) | H15: =-(SUMIF('Calcul'!$B$2:$B$85,6,'Calcul'!$I$2:$I$85)+SUMIF('Calcul'!$B$2:$B$85,6,'Calcul'!$J$2:$J$85)+SUMIF('Calcul'!$B$2:$B$85,6,'Calcul'!$Q$2:$Q$85)+SUMIF('Calcul'!$B$2:$B$85,6,'Calcul'!$N$2:$N$85)+SUMIF('Calcul'!$B$2:$B$85,6,'Calcul'!$O$2:$O$85)+SUMIF('Calcul'!$B$2:$B$85,6,'Calcul'!$P$2:$P$85)) | I15: =-(SUMIF('Calcul'!$B$2:$B$85,7,'Calcul'!$I$2:$I$85)+SUMIF('Calcul'!$B$2:$B$85,7,'Calcul'!$J$2:$J$85)+SUMIF('Calcul'!$B$2:$B$85,7,'Calcul'!$Q$2:$Q$85)+SUMIF('Calcul'!$B$2:$B$85,7,'Calcul'!$N$2:$N$85)+SUMIF('Calcul'!$B$2:$B$85,7,'Calcul'!$O$2:$O$85)+SUMIF('Calcul'!$B$2:$B$85,7,'Calcul'!$P$2:$P$85)) | J15: =SUM(C15:I15)
B16: RÉSULTAT D'EXPLOITATION (= EBITDA, sans amortissement) | C16: =SUMIF('Calcul'!$B$2:$B$85,1,'Calcul'!$R$2:$R$85) | D16: =SUMIF('Calcul'!$B$2:$B$85,2,'Calcul'!$R$2:$R$85) | E16: =SUMIF('Calcul'!$B$2:$B$85,3,'Calcul'!$R$2:$R$85) | F16: =SUMIF('Calcul'!$B$2:$B$85,4,'Calcul'!$R$2:$R$85) | G16: =SUMIF('Calcul'!$B$2:$B$85,5,'Calcul'!$R$2:$R$85) | H16: =SUMIF('Calcul'!$B$2:$B$85,6,'Calcul'!$R$2:$R$85) | I16: =SUMIF('Calcul'!$B$2:$B$85,7,'Calcul'!$R$2:$R$85) | J16: =SUM(C16:I16)
B17: Charges financières nettes | C17: =0 | D17: =0 | E17: =0 | F17: =0 | G17: =0 | H17: =0 | I17: =0 | J17: =SUM(C17:I17)
B18: Résultat des activités ordinaires avant impôt | C18: =SUMIF('Calcul'!$B$2:$B$85,1,'Calcul'!$R$2:$R$85) | D18: =SUMIF('Calcul'!$B$2:$B$85,2,'Calcul'!$R$2:$R$85) | E18: =SUMIF('Calcul'!$B$2:$B$85,3,'Calcul'!$R$2:$R$85) | F18: =SUMIF('Calcul'!$B$2:$B$85,4,'Calcul'!$R$2:$R$85) | G18: =SUMIF('Calcul'!$B$2:$B$85,5,'Calcul'!$R$2:$R$85) | H18: =SUMIF('Calcul'!$B$2:$B$85,6,'Calcul'!$R$2:$R$85) | I18: =SUMIF('Calcul'!$B$2:$B$85,7,'Calcul'!$R$2:$R$85) | J18: =SUM(C18:I18)
B19: Impôt sur les bénéfices (IS 25 % + CSS 3 %) | C19: =-MAX(0,SUMIF('Calcul'!$B$2:$B$85,1,'Calcul'!$R$2:$R$85))*'Hypothèses'!$C$54 | D19: =-MAX(0,SUMIF('Calcul'!$B$2:$B$85,2,'Calcul'!$R$2:$R$85))*'Hypothèses'!$C$54 | E19: =-MAX(0,SUMIF('Calcul'!$B$2:$B$85,3,'Calcul'!$R$2:$R$85))*'Hypothèses'!$C$54 | F19: =-MAX(0,SUMIF('Calcul'!$B$2:$B$85,4,'Calcul'!$R$2:$R$85))*'Hypothèses'!$C$54 | G19: =-MAX(0,SUMIF('Calcul'!$B$2:$B$85,5,'Calcul'!$R$2:$R$85))*'Hypothèses'!$C$54 | H19: =-MAX(0,SUMIF('Calcul'!$B$2:$B$85,6,'Calcul'!$R$2:$R$85))*'Hypothèses'!$C$54 | I19: =-MAX(0,SUMIF('Calcul'!$B$2:$B$85,7,'Calcul'!$R$2:$R$85))*'Hypothèses'!$C$54 | J19: =SUM(C19:I19)
B20: RÉSULTAT NET DE L'EXERCICE | C20: =(SUMIF('Calcul'!$B$2:$B$85,1,'Calcul'!$R$2:$R$85)-MAX(0,SUMIF('Calcul'!$B$2:$B$85,1,'Calcul'!$R$2:$R$85))*'Hypothèses'!$C$54) | D20: =(SUMIF('Calcul'!$B$2:$B$85,2,'Calcul'!$R$2:$R$85)-MAX(0,SUMIF('Calcul'!$B$2:$B$85,2,'Calcul'!$R$2:$R$85))*'Hypothèses'!$C$54) | E20: =(SUMIF('Calcul'!$B$2:$B$85,3,'Calcul'!$R$2:$R$85)-MAX(0,SUMIF('Calcul'!$B$2:$B$85,3,'Calcul'!$R$2:$R$85))*'Hypothèses'!$C$54) | F20: =(SUMIF('Calcul'!$B$2:$B$85,4,'Calcul'!$R$2:$R$85)-MAX(0,SUMIF('Calcul'!$B$2:$B$85,4,'Calcul'!$R$2:$R$85))*'Hypothèses'!$C$54) | G20: =(SUMIF('Calcul'!$B$2:$B$85,5,'Calcul'!$R$2:$R$85)-MAX(0,SUMIF('Calcul'!$B$2:$B$85,5,'Calcul'!$R$2:$R$85))*'Hypothèses'!$C$54) | H20: =(SUMIF('Calcul'!$B$2:$B$85,6,'Calcul'!$R$2:$R$85)-MAX(0,SUMIF('Calcul'!$B$2:$B$85,6,'Calcul'!$R$2:$R$85))*'Hypothèses'!$C$54) | I20: =(SUMIF('Calcul'!$B$2:$B$85,7,'Calcul'!$R$2:$R$85)-MAX(0,SUMIF('Calcul'!$B$2:$B$85,7,'Calcul'!$R$2:$R$85))*'Hypothèses'!$C$54) | J20: =SUM(C20:I20)
B21: Résultat net cumulé | C21: =(SUMIF('Calcul'!$B$2:$B$85,1,'Calcul'!$R$2:$R$85)-MAX(0,SUMIF('Calcul'!$B$2:$B$85,1,'Calcul'!$R$2:$R$85))*'Hypothèses'!$C$54) | D21: =(SUMIF('Calcul'!$B$2:$B$85,1,'Calcul'!$R$2:$R$85)-MAX(0,SUMIF('Calcul'!$B$2:$B$85,1,'Calcul'!$R$2:$R$85))*'Hypothèses'!$C$54)+(SUMIF('Calcul'!$B$2:$B$85,2,'Calcul'!$R$2:$R$85)-MAX(0,SUMIF('Calcul'!$B$2:$B$85,2,'Calcul'!$R$2:$R$85))*'Hypothèses'!$C$54) | E21: =(SUMIF('Calcul'!$B$2:$B$85,1,'Calcul'!$R$2:$R$85)-MAX(0,SUMIF('Calcul'!$B$2:$B$85,1,'Calcul'!$R$2:$R$85))*'Hypothèses'!$C$54)+(SUMIF('Calcul'!$B$2:$B$85,2,'Calcul'!$R$2:$R$85)-MAX(0,SUMIF('Calcul'!$B$2:$B$85,2,'Calcul'!$R$2:$R$85))*'Hypothèses'!$C$54)+(SUMIF('Calcul'!$B$2:$B$85,3,'Calcul'!$R$2:$R$85)-MAX(0,SUMIF('Calcul'!$B$2:$B$85,3,'Calcul'!$R$2:$R$85))*'Hypothèses'!$C$54) | F21: =(SUMIF('Calcul'!$B$2:$B$85,1,'Calcul'!$R$2:$R$85)-MAX(0,SUMIF('Calcul'!$B$2:$B$85,1,'Calcul'!$R$2:$R$85))*'Hypothèses'!$C$54)+(SUMIF('Calcul'!$B$2:$B$85,2,'Calcul'!$R$2:$R$85)-MAX(0,SUMIF('Calcul'!$B$2:$B$85,2,'Calcul'!$R$2:$R$85))*'Hypothèses'!$C$54)+(SUMIF('Calcul'!$B$2:$B$85,3,'Calcul'!$R$2:$R$85)-MAX(0,SUMIF('Calcul'!$B$2:$B$85,3,'Calcul'!$R$2:$R$85))*'Hypothèses'!$C$54)+(SUMIF('Calcul'!$B$2:$B$85,4,'Calcul'!$R$2:$R$85)-MAX(0,SUMIF('Calcul'!$B$2:$B$85,4,'Calcul'!$R$2:$R$85))*'Hypothèses'!$C$54) | G21: =(SUMIF('Calcul'!$B$2:$B$85,1,'Calcul'!$R$2:$R$85)-MAX(0,SUMIF('Calcul'!$B$2:$B$85,1,'Calcul'!$R$2:$R$85))*'Hypothèses'!$C$54)+(SUMIF('Calcul'!$B$2:$B$85,2,'Calcul'!$R$2:$R$85)-MAX(0,SUMIF('Calcul'!$B$2:$B$85,2,'Calcul'!$R$2:$R$85))*'Hypothèses'!$C$54)+(SUMIF('Calcul'!$B$2:$B$85,3,'Calcul'!$R$2:$R$85)-MAX(0,SUMIF('Calcul'!$B$2:$B$85,3,'Calcul'!$R$2:$R$85))*'Hypothèses'!$C$54)+(SUMIF('Calcul'!$B$2:$B$85,4,'Calcul'!$R$2:$R$85)-MAX(0,SUMIF('Calcul'!$B$2:$B$85,4,'Calcul'!$R$2:$R$85))*'Hypothèses'!$C$54)+(SUMIF('Calcul'!$B$2:$B$85,5,'Calcul'!$R$2:$R$85)-MAX(0,SUMIF('Calcul'!$B$2:$B$85,5,'Calcul'!$R$2:$R$85))*'Hypothèses'!$C$54) | H21: =(SUMIF('Calcul'!$B$2:$B$85,1,'Calcul'!$R$2:$R$85)-MAX(0,SUMIF('Calcul'!$B$2:$B$85,1,'Calcul'!$R$2:$R$85))*'Hypothèses'!$C$54)+(SUMIF('Calcul'!$B$2:$B$85,2,'Calcul'!$R$2:$R$85)-MAX(0,SUMIF('Calcul'!$B$2:$B$85,2,'Calcul'!$R$2:$R$85))*'Hypothèses'!$C$54)+(SUMIF('Calcul'!$B$2:$B$85,3,'Calcul'!$R$2:$R$85)-MAX(0,SUMIF('Calcul'!$B$2:$B$85,3,'Calcul'!$R$2:$R$85))*'Hypothèses'!$C$54)+(SUMIF('Calcul'!$B$2:$B$85,4,'Calcul'!$R$2:$R$85)-MAX(0,SUMIF('Calcul'!$B$2:$B$85,4,'Calcul'!$R$2:$R$85))*'Hypothèses'!$C$54)+(SUMIF('Calcul'!$B$2:$B$85,5,'Calcul'!$R$2:$R$85)-MAX(0,SUMIF('Calcul'!$B$2:$B$85,5,'Calcul'!$R$2:$R$85))*'Hypothèses'!$C$54)+(SUMIF('Calcul'!$B$2:$B$85,6,'Calcul'!$R$2:$R$85)-MAX(0,SUMIF('Calcul'!$B$2:$B$85,6,'Calcul'!$R$2:$R$85))*'Hypothèses'!$C$54) | I21: =(SUMIF('Calcul'!$B$2:$B$85,1,'Calcul'!$R$2:$R$85)-MAX(0,SUMIF('Calcul'!$B$2:$B$85,1,'Calcul'!$R$2:$R$85))*'Hypothèses'!$C$54)+(SUMIF('Calcul'!$B$2:$B$85,2,'Calcul'!$R$2:$R$85)-MAX(0,SUMIF('Calcul'!$B$2:$B$85,2,'Calcul'!$R$2:$R$85))*'Hypothèses'!$C$54)+(SUMIF('Calcul'!$B$2:$B$85,3,'Calcul'!$R$2:$R$85)-MAX(0,SUMIF('Calcul'!$B$2:$B$85,3,'Calcul'!$R$2:$R$85))*'Hypothèses'!$C$54)+(SUMIF('Calcul'!$B$2:$B$85,4,'Calcul'!$R$2:$R$85)-MAX(0,SUMIF('Calcul'!$B$2:$B$85,4,'Calcul'!$R$2:$R$85))*'Hypothèses'!$C$54)+(SUMIF('Calcul'!$B$2:$B$85,5,'Calcul'!$R$2:$R$85)-MAX(0,SUMIF('Calcul'!$B$2:$B$85,5,'Calcul'!$R$2:$R$85))*'Hypothèses'!$C$54)+(SUMIF('Calcul'!$B$2:$B$85,6,'Calcul'!$R$2:$R$85)-MAX(0,SUMIF('Calcul'!$B$2:$B$85,6,'Calcul'!$R$2:$R$85))*'Hypothèses'!$C$54)+(SUMIF('Calcul'!$B$2:$B$85,7,'Calcul'!$R$2:$R$85)-MAX(0,SUMIF('Calcul'!$B$2:$B$85,7,'Calcul'!$R$2:$R$85))*'Hypothèses'!$C$54) | J21: =I21
B23: Aucun amortissement de machine : le financement est porté par le leasing (location). Aucune charge financière bancaire : zéro emprunt.

Sheet Bilan
B1: Bilan prévisionnel
B2: Présentation normée (SCE Tunisie). En DT — machines en leasing = location simple (hors bilan). Équilibré par construction.
C4: An 1 | D4: An 2 | E4: An 3 | F4: An 4 | G4: An 5 | H4: An 6 | I4: An 7
B5: ACTIFS
B6: Actifs non courants (immobilisations) | C6: =0 | D6: =0 | E6: =0 | F6: =0 | G6: =0 | H6: =0 | I6: =0
B7: Actifs courants — trésorerie & équivalents | C7: ='Calcul'!$T$13 | D7: ='Calcul'!$T$25-'Hypothèses'!$C$56*((SUMIF('Calcul'!$B$2:$B$85,1,'Calcul'!$R$2:$R$85)-MAX(0,SUMIF('Calcul'!$B$2:$B$85,1,'Calcul'!$R$2:$R$85))*'Hypothèses'!$C$54)) | E7: ='Calcul'!$T$37-'Hypothèses'!$C$56*((SUMIF('Calcul'!$B$2:$B$85,1,'Calcul'!$R$2:$R$85)-MAX(0,SUMIF('Calcul'!$B$2:$B$85,1,'Calcul'!$R$2:$R$85))*'Hypothèses'!$C$54)+(SUMIF('Calcul'!$B$2:$B$85,2,'Calcul'!$R$2:$R$85)-MAX(0,SUMIF('Calcul'!$B$2:$B$85,2,'Calcul'!$R$2:$R$85))*'Hypothèses'!$C$54)) | F7: ='Calcul'!$T$49-'Hypothèses'!$C$56*((SUMIF('Calcul'!$B$2:$B$85,1,'Calcul'!$R$2:$R$85)-MAX(0,SUMIF('Calcul'!$B$2:$B$85,1,'Calcul'!$R$2:$R$85))*'Hypothèses'!$C$54)+(SUMIF('Calcul'!$B$2:$B$85,2,'Calcul'!$R$2:$R$85)-MAX(0,SUMIF('Calcul'!$B$2:$B$85,2,'Calcul'!$R$2:$R$85))*'Hypothèses'!$C$54)+(SUMIF('Calcul'!$B$2:$B$85,3,'Calcul'!$R$2:$R$85)-MAX(0,SUMIF('Calcul'!$B$2:$B$85,3,'Calcul'!$R$2:$R$85))*'Hypothèses'!$C$54)) | G7: ='Calcul'!$T$61-'Hypothèses'!$C$56*((SUMIF('Calcul'!$B$2:$B$85,1,'Calcul'!$R$2:$R$85)-MAX(0,SUMIF('Calcul'!$B$2:$B$85,1,'Calcul'!$R$2:$R$85))*'Hypothèses'!$C$54)+(SUMIF('Calcul'!$B$2:$B$85,2,'Calcul'!$R$2:$R$85)-MAX(0,SUMIF('Calcul'!$B$2:$B$85,2,'Calcul'!$R$2:$R$85))*'Hypothèses'!$C$54)+(SUMIF('Calcul'!$B$2:$B$85,3,'Calcul'!$R$2:$R$85)-MAX(0,SUMIF('Calcul'!$B$2:$B$85,3,'Calcul'!$R$2:$R$85))*'Hypothèses'!$C$54)+(SUMIF('Calcul'!$B$2:$B$85,4,'Calcul'!$R$2:$R$85)-MAX(0,SUMIF('Calcul'!$B$2:$B$85,4,'Calcul'!$R$2:$R$85))*'Hypothèses'!$C$54)) | H7: ='Calcul'!$T$73-'Hypothèses'!$C$56*((SUMIF('Calcul'!$B$2:$B$85,1,'Calcul'!$R$2:$R$85)-MAX(0,SUMIF('Calcul'!$B$2:$B$85,1,'Calcul'!$R$2:$R$85))*'Hypothèses'!$C$54)+(SUMIF('Calcul'!$B$2:$B$85,2,'Calcul'!$R$2:$R$85)-MAX(0,SUMIF('Calcul'!$B$2:$B$85,2,'Calcul'!$R$2:$R$85))*'Hypothèses'!$C$54)+(SUMIF('Calcul'!$B$2:$B$85,3,'Calcul'!$R$2:$R$85)-MAX(0,SUMIF('Calcul'!$B$2:$B$85,3,'Calcul'!$R$2:$R$85))*'Hypothèses'!$C$54)+(SUMIF('Calcul'!$B$2:$B$85,4,'Calcul'!$R$2:$R$85)-MAX(0,SUMIF('Calcul'!$B$2:$B$85,4,'Calcul'!$R$2:$R$85))*'Hypothèses'!$C$54)+(SUMIF('Calcul'!$B$2:$B$85,5,'Calcul'!$R$2:$R$85)-MAX(0,SUMIF('Calcul'!$B$2:$B$85,5,'Calcul'!$R$2:$R$85))*'Hypothèses'!$C$54)) | I7: ='Calcul'!$T$85-'Hypothèses'!$C$56*((SUMIF('Calcul'!$B$2:$B$85,1,'Calcul'!$R$2:$R$85)-MAX(0,SUMIF('Calcul'!$B$2:$B$85,1,'Calcul'!$R$2:$R$85))*'Hypothèses'!$C$54)+(SUMIF('Calcul'!$B$2:$B$85,2,'Calcul'!$R$2:$R$85)-MAX(0,SUMIF('Calcul'!$B$2:$B$85,2,'Calcul'!$R$2:$R$85))*'Hypothèses'!$C$54)+(SUMIF('Calcul'!$B$2:$B$85,3,'Calcul'!$R$2:$R$85)-MAX(0,SUMIF('Calcul'!$B$2:$B$85,3,'Calcul'!$R$2:$R$85))*'Hypothèses'!$C$54)+(SUMIF('Calcul'!$B$2:$B$85,4,'Calcul'!$R$2:$R$85)-MAX(0,SUMIF('Calcul'!$B$2:$B$85,4,'Calcul'!$R$2:$R$85))*'Hypothèses'!$C$54)+(SUMIF('Calcul'!$B$2:$B$85,5,'Calcul'!$R$2:$R$85)-MAX(0,SUMIF('Calcul'!$B$2:$B$85,5,'Calcul'!$R$2:$R$85))*'Hypothèses'!$C$54)+(SUMIF('Calcul'!$B$2:$B$85,6,'Calcul'!$R$2:$R$85)-MAX(0,SUMIF('Calcul'!$B$2:$B$85,6,'Calcul'!$R$2:$R$85))*'Hypothèses'!$C$54))
B8: TOTAL DES ACTIFS | C8: =C6+C7 | D8: =D6+D7 | E8: =E6+E7 | F8: =F6+F7 | G8: =G6+G7 | H8: =H6+H7 | I8: =I6+I7
B9: CAPITAUX PROPRES & PASSIFS
B10: Capital social | C10: ='Hypothèses'!$C$55 | D10: ='Hypothèses'!$C$55 | E10: ='Hypothèses'!$C$55 | F10: ='Hypothèses'!$C$55 | G10: ='Hypothèses'!$C$55 | H10: ='Hypothèses'!$C$55 | I10: ='Hypothèses'!$C$55
B11: Réserves & résultats reportés | C11: =(1-'Hypothèses'!$C$56)*((SUMIF('Calcul'!$B$2:$B$85,1,'Calcul'!$R$2:$R$85)-MAX(0,SUMIF('Calcul'!$B$2:$B$85,1,'Calcul'!$R$2:$R$85))*'Hypothèses'!$C$54)) | D11: =(1-'Hypothèses'!$C$56)*((SUMIF('Calcul'!$B$2:$B$85,1,'Calcul'!$R$2:$R$85)-MAX(0,SUMIF('Calcul'!$B$2:$B$85,1,'Calcul'!$R$2:$R$85))*'Hypothèses'!$C$54)+(SUMIF('Calcul'!$B$2:$B$85,2,'Calcul'!$R$2:$R$85)-MAX(0,SUMIF('Calcul'!$B$2:$B$85,2,'Calcul'!$R$2:$R$85))*'Hypothèses'!$C$54)) | E11: =(1-'Hypothèses'!$C$56)*((SUMIF('Calcul'!$B$2:$B$85,1,'Calcul'!$R$2:$R$85)-MAX(0,SUMIF('Calcul'!$B$2:$B$85,1,'Calcul'!$R$2:$R$85))*'Hypothèses'!$C$54)+(SUMIF('Calcul'!$B$2:$B$85,2,'Calcul'!$R$2:$R$85)-MAX(0,SUMIF('Calcul'!$B$2:$B$85,2,'Calcul'!$R$2:$R$85))*'Hypothèses'!$C$54)+(SUMIF('Calcul'!$B$2:$B$85,3,'Calcul'!$R$2:$R$85)-MAX(0,SUMIF('Calcul'!$B$2:$B$85,3,'Calcul'!$R$2:$R$85))*'Hypothèses'!$C$54)) | F11: =(1-'Hypothèses'!$C$56)*((SUMIF('Calcul'!$B$2:$B$85,1,'Calcul'!$R$2:$R$85)-MAX(0,SUMIF('Calcul'!$B$2:$B$85,1,'Calcul'!$R$2:$R$85))*'Hypothèses'!$C$54)+(SUMIF('Calcul'!$B$2:$B$85,2,'Calcul'!$R$2:$R$85)-MAX(0,SUMIF('Calcul'!$B$2:$B$85,2,'Calcul'!$R$2:$R$85))*'Hypothèses'!$C$54)+(SUMIF('Calcul'!$B$2:$B$85,3,'Calcul'!$R$2:$R$85)-MAX(0,SUMIF('Calcul'!$B$2:$B$85,3,'Calcul'!$R$2:$R$85))*'Hypothèses'!$C$54)+(SUMIF('Calcul'!$B$2:$B$85,4,'Calcul'!$R$2:$R$85)-MAX(0,SUMIF('Calcul'!$B$2:$B$85,4,'Calcul'!$R$2:$R$85))*'Hypothèses'!$C$54)) | G11: =(1-'Hypothèses'!$C$56)*((SUMIF('Calcul'!$B$2:$B$85,1,'Calcul'!$R$2:$R$85)-MAX(0,SUMIF('Calcul'!$B$2:$B$85,1,'Calcul'!$R$2:$R$85))*'Hypothèses'!$C$54)+(SUMIF('Calcul'!$B$2:$B$85,2,'Calcul'!$R$2:$R$85)-MAX(0,SUMIF('Calcul'!$B$2:$B$85,2,'Calcul'!$R$2:$R$85))*'Hypothèses'!$C$54)+(SUMIF('Calcul'!$B$2:$B$85,3,'Calcul'!$R$2:$R$85)-MAX(0,SUMIF('Calcul'!$B$2:$B$85,3,'Calcul'!$R$2:$R$85))*'Hypothèses'!$C$54)+(SUMIF('Calcul'!$B$2:$B$85,4,'Calcul'!$R$2:$R$85)-MAX(0,SUMIF('Calcul'!$B$2:$B$85,4,'Calcul'!$R$2:$R$85))*'Hypothèses'!$C$54)+(SUMIF('Calcul'!$B$2:$B$85,5,'Calcul'!$R$2:$R$85)-MAX(0,SUMIF('Calcul'!$B$2:$B$85,5,'Calcul'!$R$2:$R$85))*'Hypothèses'!$C$54)) | H11: =(1-'Hypothèses'!$C$56)*((SUMIF('Calcul'!$B$2:$B$85,1,'Calcul'!$R$2:$R$85)-MAX(0,SUMIF('Calcul'!$B$2:$B$85,1,'Calcul'!$R$2:$R$85))*'Hypothèses'!$C$54)+(SUMIF('Calcul'!$B$2:$B$85,2,'Calcul'!$R$2:$R$85)-MAX(0,SUMIF('Calcul'!$B$2:$B$85,2,'Calcul'!$R$2:$R$85))*'Hypothèses'!$C$54)+(SUMIF('Calcul'!$B$2:$B$85,3,'Calcul'!$R$2:$R$85)-MAX(0,SUMIF('Calcul'!$B$2:$B$85,3,'Calcul'!$R$2:$R$85))*'Hypothèses'!$C$54)+(SUMIF('Calcul'!$B$2:$B$85,4,'Calcul'!$R$2:$R$85)-MAX(0,SUMIF('Calcul'!$B$2:$B$85,4,'Calcul'!$R$2:$R$85))*'Hypothèses'!$C$54)+(SUMIF('Calcul'!$B$2:$B$85,5,'Calcul'!$R$2:$R$85)-MAX(0,SUMIF('Calcul'!$B$2:$B$85,5,'Calcul'!$R$2:$R$85))*'Hypothèses'!$C$54)+(SUMIF('Calcul'!$B$2:$B$85,6,'Calcul'!$R$2:$R$85)-MAX(0,SUMIF('Calcul'!$B$2:$B$85,6,'Calcul'!$R$2:$R$85))*'Hypothèses'!$C$54)) | I11: =(1-'Hypothèses'!$C$56)*((SUMIF('Calcul'!$B$2:$B$85,1,'Calcul'!$R$2:$R$85)-MAX(0,SUMIF('Calcul'!$B$2:$B$85,1,'Calcul'!$R$2:$R$85))*'Hypothèses'!$C$54)+(SUMIF('Calcul'!$B$2:$B$85,2,'Calcul'!$R$2:$R$85)-MAX(0,SUMIF('Calcul'!$B$2:$B$85,2,'Calcul'!$R$2:$R$85))*'Hypothèses'!$C$54)+(SUMIF('Calcul'!$B$2:$B$85,3,'Calcul'!$R$2:$R$85)-MAX(0,SUMIF('Calcul'!$B$2:$B$85,3,'Calcul'!$R$2:$R$85))*'Hypothèses'!$C$54)+(SUMIF('Calcul'!$B$2:$B$85,4,'Calcul'!$R$2:$R$85)-MAX(0,SUMIF('Calcul'!$B$2:$B$85,4,'Calcul'!$R$2:$R$85))*'Hypothèses'!$C$54)+(SUMIF('Calcul'!$B$2:$B$85,5,'Calcul'!$R$2:$R$85)-MAX(0,SUMIF('Calcul'!$B$2:$B$85,5,'Calcul'!$R$2:$R$85))*'Hypothèses'!$C$54)+(SUMIF('Calcul'!$B$2:$B$85,6,'Calcul'!$R$2:$R$85)-MAX(0,SUMIF('Calcul'!$B$2:$B$85,6,'Calcul'!$R$2:$R$85))*'Hypothèses'!$C$54)+(SUMIF('Calcul'!$B$2:$B$85,7,'Calcul'!$R$2:$R$85)-MAX(0,SUMIF('Calcul'!$B$2:$B$85,7,'Calcul'!$R$2:$R$85))*'Hypothèses'!$C$54))
B12: Total des capitaux propres | C12: =C10+C11 | D12: =D10+D11 | E12: =E10+E11 | F12: =F10+F11 | G12: =G10+G11 | H12: =H10+H11 | I12: =I10+I11 | J12: =SUM(C12:I12)
B13: Passifs courants — dividendes à payer | C13: ='Hypothèses'!$C$56*(SUMIF('Calcul'!$B$2:$B$85,1,'Calcul'!$R$2:$R$85)-MAX(0,SUMIF('Calcul'!$B$2:$B$85,1,'Calcul'!$R$2:$R$85))*'Hypothèses'!$C$54) | D13: ='Hypothèses'!$C$56*(SUMIF('Calcul'!$B$2:$B$85,2,'Calcul'!$R$2:$R$85)-MAX(0,SUMIF('Calcul'!$B$2:$B$85,2,'Calcul'!$R$2:$R$85))*'Hypothèses'!$C$54) | E13: ='Hypothèses'!$C$56*(SUMIF('Calcul'!$B$2:$B$85,3,'Calcul'!$R$2:$R$85)-MAX(0,SUMIF('Calcul'!$B$2:$B$85,3,'Calcul'!$R$2:$R$85))*'Hypothèses'!$C$54) | F13: ='Hypothèses'!$C$56*(SUMIF('Calcul'!$B$2:$B$85,4,'Calcul'!$R$2:$R$85)-MAX(0,SUMIF('Calcul'!$B$2:$B$85,4,'Calcul'!$R$2:$R$85))*'Hypothèses'!$C$54) | G13: ='Hypothèses'!$C$56*(SUMIF('Calcul'!$B$2:$B$85,5,'Calcul'!$R$2:$R$85)-MAX(0,SUMIF('Calcul'!$B$2:$B$85,5,'Calcul'!$R$2:$R$85))*'Hypothèses'!$C$54) | H13: ='Hypothèses'!$C$56*(SUMIF('Calcul'!$B$2:$B$85,6,'Calcul'!$R$2:$R$85)-MAX(0,SUMIF('Calcul'!$B$2:$B$85,6,'Calcul'!$R$2:$R$85))*'Hypothèses'!$C$54) | I13: ='Hypothèses'!$C$56*(SUMIF('Calcul'!$B$2:$B$85,7,'Calcul'!$R$2:$R$85)-MAX(0,SUMIF('Calcul'!$B$2:$B$85,7,'Calcul'!$R$2:$R$85))*'Hypothèses'!$C$54)
B14: Passifs courants — impôt à payer (exigible N+1) | C14: =MAX(0,SUMIF('Calcul'!$B$2:$B$85,1,'Calcul'!$R$2:$R$85))*'Hypothèses'!$C$54 | D14: =MAX(0,SUMIF('Calcul'!$B$2:$B$85,2,'Calcul'!$R$2:$R$85))*'Hypothèses'!$C$54 | E14: =MAX(0,SUMIF('Calcul'!$B$2:$B$85,3,'Calcul'!$R$2:$R$85))*'Hypothèses'!$C$54 | F14: =MAX(0,SUMIF('Calcul'!$B$2:$B$85,4,'Calcul'!$R$2:$R$85))*'Hypothèses'!$C$54 | G14: =MAX(0,SUMIF('Calcul'!$B$2:$B$85,5,'Calcul'!$R$2:$R$85))*'Hypothèses'!$C$54 | H14: =MAX(0,SUMIF('Calcul'!$B$2:$B$85,6,'Calcul'!$R$2:$R$85))*'Hypothèses'!$C$54 | I14: =MAX(0,SUMIF('Calcul'!$B$2:$B$85,7,'Calcul'!$R$2:$R$85))*'Hypothèses'!$C$54
B15: Total des passifs courants | C15: =C13+C14 | D15: =D13+D14 | E15: =E13+E14 | F15: =F13+F14 | G15: =G13+G14 | H15: =H13+H14 | I15: =I13+I14 | J15: =SUM(C15:I15)
B16: TOTAL CAPITAUX PROPRES & PASSIFS | C16: =C12+C15 | D16: =D12+D15 | E16: =E12+E15 | F16: =F12+F15 | G16: =G12+G15 | H16: =H12+H15 | I16: =I12+I15
B17: Contrôle (Actif − Passif ≈ 0) | C17: =C8-C16 | D17: =D8-D16 | E17: =E8-E16 | F17: =F8-F16 | G17: =G8-G16 | H17: =H8-H16 | I17: =I8-I16

Sheet Flux de trésorerie
B1: État de flux de trésorerie prévisionnel
B2: Présentation par activité (norme tunisienne). En DT — aucun flux d'investissement : les machines sont en leasing.
C4: An 1 | D4: An 2 | E4: An 3 | F4: An 4 | G4: An 5 | H4: An 6 | I4: An 7 | J4: Total 7 ans
B5: FLUX LIÉS À L'EXPLOITATION
B6: EBITDA (capacité d'autofinancement) | C6: =SUMIF('Calcul'!$B$2:$B$85,1,'Calcul'!$R$2:$R$85) | D6: =SUMIF('Calcul'!$B$2:$B$85,2,'Calcul'!$R$2:$R$85) | E6: =SUMIF('Calcul'!$B$2:$B$85,3,'Calcul'!$R$2:$R$85) | F6: =SUMIF('Calcul'!$B$2:$B$85,4,'Calcul'!$R$2:$R$85) | G6: =SUMIF('Calcul'!$B$2:$B$85,5,'Calcul'!$R$2:$R$85) | H6: =SUMIF('Calcul'!$B$2:$B$85,6,'Calcul'!$R$2:$R$85) | I6: =SUMIF('Calcul'!$B$2:$B$85,7,'Calcul'!$R$2:$R$85) | J6: =SUM(C6:I6)
B7: (−) Impôt décaissé sur l'exercice | C7: =-SUMIF('Calcul'!$B$2:$B$85,1,'Calcul'!$S$2:$S$85) | D7: =-SUMIF('Calcul'!$B$2:$B$85,2,'Calcul'!$S$2:$S$85) | E7: =-SUMIF('Calcul'!$B$2:$B$85,3,'Calcul'!$S$2:$S$85) | F7: =-SUMIF('Calcul'!$B$2:$B$85,4,'Calcul'!$S$2:$S$85) | G7: =-SUMIF('Calcul'!$B$2:$B$85,5,'Calcul'!$S$2:$S$85) | H7: =-SUMIF('Calcul'!$B$2:$B$85,6,'Calcul'!$S$2:$S$85) | I7: =-SUMIF('Calcul'!$B$2:$B$85,7,'Calcul'!$S$2:$S$85) | J7: =SUM(C7:I7)
B8: Flux net de trésorerie d'exploitation | C8: =C6+C7 | D8: =D6+D7 | E8: =E6+E7 | F8: =F6+F7 | G8: =G6+G7 | H8: =H6+H7 | I8: =I6+I7 | J8: =SUM(C8:I8)
B9: FLUX LIÉS À L'INVESTISSEMENT
B10: Acquisitions d'immobilisations (machines en leasing) | C10: =0 | D10: =0 | E10: =0 | F10: =0 | G10: =0 | H10: =0 | I10: =0 | J10: =SUM(C10:I10)
B11: Flux net de trésorerie d'investissement | C11: =0 | D11: =0 | E11: =0 | F11: =0 | G11: =0 | H11: =0 | I11: =0 | J11: =SUM(C11:I11)
B12: FLUX LIÉS AU FINANCEMENT
B13: Apport en capital | C13: ='Hypothèses'!$C$55 | D13: =0 | E13: =0 | F13: =0 | G13: =0 | H13: =0 | I13: =0 | J13: =SUM(C13:I13)
B14: Dividendes versés (au titre de l'exercice N-1) | C14: =0 | D14: =-'Hypothèses'!$C$56*(SUMIF('Calcul'!$B$2:$B$85,1,'Calcul'!$R$2:$R$85)-MAX(0,SUMIF('Calcul'!$B$2:$B$85,1,'Calcul'!$R$2:$R$85))*'Hypothèses'!$C$54) | E14: =-'Hypothèses'!$C$56*(SUMIF('Calcul'!$B$2:$B$85,2,'Calcul'!$R$2:$R$85)-MAX(0,SUMIF('Calcul'!$B$2:$B$85,2,'Calcul'!$R$2:$R$85))*'Hypothèses'!$C$54) | F14: =-'Hypothèses'!$C$56*(SUMIF('Calcul'!$B$2:$B$85,3,'Calcul'!$R$2:$R$85)-MAX(0,SUMIF('Calcul'!$B$2:$B$85,3,'Calcul'!$R$2:$R$85))*'Hypothèses'!$C$54) | G14: =-'Hypothèses'!$C$56*(SUMIF('Calcul'!$B$2:$B$85,4,'Calcul'!$R$2:$R$85)-MAX(0,SUMIF('Calcul'!$B$2:$B$85,4,'Calcul'!$R$2:$R$85))*'Hypothèses'!$C$54) | H14: =-'Hypothèses'!$C$56*(SUMIF('Calcul'!$B$2:$B$85,5,'Calcul'!$R$2:$R$85)-MAX(0,SUMIF('Calcul'!$B$2:$B$85,5,'Calcul'!$R$2:$R$85))*'Hypothèses'!$C$54) | I14: =-'Hypothèses'!$C$56*(SUMIF('Calcul'!$B$2:$B$85,6,'Calcul'!$R$2:$R$85)-MAX(0,SUMIF('Calcul'!$B$2:$B$85,6,'Calcul'!$R$2:$R$85))*'Hypothèses'!$C$54) | J14: =SUM(C14:I14)
B15: Flux net de trésorerie de financement | C15: =C13+C14 | D15: =D13+D14 | E15: =E13+E14 | F15: =F13+F14 | G15: =G13+G14 | H15: =H13+H14 | I15: =I13+I14 | J15: =SUM(C15:I15)
B16: VARIATION DE TRÉSORERIE | C16: =C8+C11+C15 | D16: =D8+D11+D15 | E16: =E8+E11+E15 | F16: =F8+F11+F15 | G16: =G8+G11+G15 | H16: =H8+H11+H15 | I16: =I8+I11+I15 | J16: =SUM(C16:I16)
B17: Trésorerie à l'ouverture | C17: =0 | D17: =C18 | E17: =D18 | F17: =E18 | G17: =F18 | H17: =G18 | I17: =H18
B18: Trésorerie à la clôture | C18: =C17+C16 | D18: =D17+D16 | E18: =E17+E16 | F18: =F17+F16 | G18: =G17+G16 | H18: =H17+H16 | I18: =I17+I16
B20: Trésorerie minimale sur 84 mois (avant distributions) | C20: =MIN('Calcul'!$T$2:$T$85) | D20: → le capital de 300 k suffit comme fonds de roulement, sans dette bancaire

Sheet Ratios financiers
B1: Ratios & indicateurs financiers
B2: Agrégats et ratios usuels d'analyse crédit (EBITDA, marges, couverture, rentabilité). Recalcul automatique.
C4: An 1 | D4: An 2 | E4: An 3 | F4: An 4 | G4: An 5 | H4: An 6 | I4: An 7 | J4: Total 7 ans
B5: SOLDES & AGRÉGATS
B6: Chiffre d'affaires (revenus) | C6: =SUMIF('Calcul'!$B$2:$B$85,1,'Calcul'!$H$2:$H$85) | D6: =SUMIF('Calcul'!$B$2:$B$85,2,'Calcul'!$H$2:$H$85) | E6: =SUMIF('Calcul'!$B$2:$B$85,3,'Calcul'!$H$2:$H$85) | F6: =SUMIF('Calcul'!$B$2:$B$85,4,'Calcul'!$H$2:$H$85) | G6: =SUMIF('Calcul'!$B$2:$B$85,5,'Calcul'!$H$2:$H$85) | H6: =SUMIF('Calcul'!$B$2:$B$85,6,'Calcul'!$H$2:$H$85) | I6: =SUMIF('Calcul'!$B$2:$B$85,7,'Calcul'!$H$2:$H$85) | J6: =SUM(C6:I6)
B7: Croissance du chiffre d'affaires | C7: ="—" | D7: =SUMIF('Calcul'!$B$2:$B$85,2,'Calcul'!$H$2:$H$85)/SUMIF('Calcul'!$B$2:$B$85,1,'Calcul'!$H$2:$H$85)-1 | E7: =SUMIF('Calcul'!$B$2:$B$85,3,'Calcul'!$H$2:$H$85)/SUMIF('Calcul'!$B$2:$B$85,2,'Calcul'!$H$2:$H$85)-1 | F7: =SUMIF('Calcul'!$B$2:$B$85,4,'Calcul'!$H$2:$H$85)/SUMIF('Calcul'!$B$2:$B$85,3,'Calcul'!$H$2:$H$85)-1 | G7: =SUMIF('Calcul'!$B$2:$B$85,5,'Calcul'!$H$2:$H$85)/SUMIF('Calcul'!$B$2:$B$85,4,'Calcul'!$H$2:$H$85)-1 | H7: =SUMIF('Calcul'!$B$2:$B$85,6,'Calcul'!$H$2:$H$85)/SUMIF('Calcul'!$B$2:$B$85,5,'Calcul'!$H$2:$H$85)-1 | I7: =SUMIF('Calcul'!$B$2:$B$85,7,'Calcul'!$H$2:$H$85)/SUMIF('Calcul'!$B$2:$B$85,6,'Calcul'!$H$2:$H$85)-1
B8: EBITDA (excédent brut d'exploitation) | C8: =SUMIF('Calcul'!$B$2:$B$85,1,'Calcul'!$R$2:$R$85) | D8: =SUMIF('Calcul'!$B$2:$B$85,2,'Calcul'!$R$2:$R$85) | E8: =SUMIF('Calcul'!$B$2:$B$85,3,'Calcul'!$R$2:$R$85) | F8: =SUMIF('Calcul'!$B$2:$B$85,4,'Calcul'!$R$2:$R$85) | G8: =SUMIF('Calcul'!$B$2:$B$85,5,'Calcul'!$R$2:$R$85) | H8: =SUMIF('Calcul'!$B$2:$B$85,6,'Calcul'!$R$2:$R$85) | I8: =SUMIF('Calcul'!$B$2:$B$85,7,'Calcul'!$R$2:$R$85) | J8: =SUM(C8:I8)
B9: EBIT (résultat d'exploitation) | C9: =SUMIF('Calcul'!$B$2:$B$85,1,'Calcul'!$R$2:$R$85) | D9: =SUMIF('Calcul'!$B$2:$B$85,2,'Calcul'!$R$2:$R$85) | E9: =SUMIF('Calcul'!$B$2:$B$85,3,'Calcul'!$R$2:$R$85) | F9: =SUMIF('Calcul'!$B$2:$B$85,4,'Calcul'!$R$2:$R$85) | G9: =SUMIF('Calcul'!$B$2:$B$85,5,'Calcul'!$R$2:$R$85) | H9: =SUMIF('Calcul'!$B$2:$B$85,6,'Calcul'!$R$2:$R$85) | I9: =SUMIF('Calcul'!$B$2:$B$85,7,'Calcul'!$R$2:$R$85) | J9: =SUM(C9:I9)
B10: Capacité d'autofinancement (CAF) | C10: =(SUMIF('Calcul'!$B$2:$B$85,1,'Calcul'!$R$2:$R$85)-MAX(0,SUMIF('Calcul'!$B$2:$B$85,1,'Calcul'!$R$2:$R$85))*'Hypothèses'!$C$54) | D10: =(SUMIF('Calcul'!$B$2:$B$85,2,'Calcul'!$R$2:$R$85)-MAX(0,SUMIF('Calcul'!$B$2:$B$85,2,'Calcul'!$R$2:$R$85))*'Hypothèses'!$C$54) | E10: =(SUMIF('Calcul'!$B$2:$B$85,3,'Calcul'!$R$2:$R$85)-MAX(0,SUMIF('Calcul'!$B$2:$B$85,3,'Calcul'!$R$2:$R$85))*'Hypothèses'!$C$54) | F10: =(SUMIF('Calcul'!$B$2:$B$85,4,'Calcul'!$R$2:$R$85)-MAX(0,SUMIF('Calcul'!$B$2:$B$85,4,'Calcul'!$R$2:$R$85))*'Hypothèses'!$C$54) | G10: =(SUMIF('Calcul'!$B$2:$B$85,5,'Calcul'!$R$2:$R$85)-MAX(0,SUMIF('Calcul'!$B$2:$B$85,5,'Calcul'!$R$2:$R$85))*'Hypothèses'!$C$54) | H10: =(SUMIF('Calcul'!$B$2:$B$85,6,'Calcul'!$R$2:$R$85)-MAX(0,SUMIF('Calcul'!$B$2:$B$85,6,'Calcul'!$R$2:$R$85))*'Hypothèses'!$C$54) | I10: =(SUMIF('Calcul'!$B$2:$B$85,7,'Calcul'!$R$2:$R$85)-MAX(0,SUMIF('Calcul'!$B$2:$B$85,7,'Calcul'!$R$2:$R$85))*'Hypothèses'!$C$54) | J10: =SUM(C10:I10)
B11: Résultat net | C11: =(SUMIF('Calcul'!$B$2:$B$85,1,'Calcul'!$R$2:$R$85)-MAX(0,SUMIF('Calcul'!$B$2:$B$85,1,'Calcul'!$R$2:$R$85))*'Hypothèses'!$C$54) | D11: =(SUMIF('Calcul'!$B$2:$B$85,2,'Calcul'!$R$2:$R$85)-MAX(0,SUMIF('Calcul'!$B$2:$B$85,2,'Calcul'!$R$2:$R$85))*'Hypothèses'!$C$54) | E11: =(SUMIF('Calcul'!$B$2:$B$85,3,'Calcul'!$R$2:$R$85)-MAX(0,SUMIF('Calcul'!$B$2:$B$85,3,'Calcul'!$R$2:$R$85))*'Hypothèses'!$C$54) | F11: =(SUMIF('Calcul'!$B$2:$B$85,4,'Calcul'!$R$2:$R$85)-MAX(0,SUMIF('Calcul'!$B$2:$B$85,4,'Calcul'!$R$2:$R$85))*'Hypothèses'!$C$54) | G11: =(SUMIF('Calcul'!$B$2:$B$85,5,'Calcul'!$R$2:$R$85)-MAX(0,SUMIF('Calcul'!$B$2:$B$85,5,'Calcul'!$R$2:$R$85))*'Hypothèses'!$C$54) | H11: =(SUMIF('Calcul'!$B$2:$B$85,6,'Calcul'!$R$2:$R$85)-MAX(0,SUMIF('Calcul'!$B$2:$B$85,6,'Calcul'!$R$2:$R$85))*'Hypothèses'!$C$54) | I11: =(SUMIF('Calcul'!$B$2:$B$85,7,'Calcul'!$R$2:$R$85)-MAX(0,SUMIF('Calcul'!$B$2:$B$85,7,'Calcul'!$R$2:$R$85))*'Hypothèses'!$C$54) | J11: =SUM(C11:I11)
B12: MARGES
B13: Marge d'EBITDA (% du CA) | C13: =SUMIF('Calcul'!$B$2:$B$85,1,'Calcul'!$R$2:$R$85)/SUMIF('Calcul'!$B$2:$B$85,1,'Calcul'!$H$2:$H$85) | D13: =SUMIF('Calcul'!$B$2:$B$85,2,'Calcul'!$R$2:$R$85)/SUMIF('Calcul'!$B$2:$B$85,2,'Calcul'!$H$2:$H$85) | E13: =SUMIF('Calcul'!$B$2:$B$85,3,'Calcul'!$R$2:$R$85)/SUMIF('Calcul'!$B$2:$B$85,3,'Calcul'!$H$2:$H$85) | F13: =SUMIF('Calcul'!$B$2:$B$85,4,'Calcul'!$R$2:$R$85)/SUMIF('Calcul'!$B$2:$B$85,4,'Calcul'!$H$2:$H$85) | G13: =SUMIF('Calcul'!$B$2:$B$85,5,'Calcul'!$R$2:$R$85)/SUMIF('Calcul'!$B$2:$B$85,5,'Calcul'!$H$2:$H$85) | H13: =SUMIF('Calcul'!$B$2:$B$85,6,'Calcul'!$R$2:$R$85)/SUMIF('Calcul'!$B$2:$B$85,6,'Calcul'!$H$2:$H$85) | I13: =SUMIF('Calcul'!$B$2:$B$85,7,'Calcul'!$R$2:$R$85)/SUMIF('Calcul'!$B$2:$B$85,7,'Calcul'!$H$2:$H$85)
B14: Marge nette (% du CA) | C14: =(SUMIF('Calcul'!$B$2:$B$85,1,'Calcul'!$R$2:$R$85)-MAX(0,SUMIF('Calcul'!$B$2:$B$85,1,'Calcul'!$R$2:$R$85))*'Hypothèses'!$C$54)/SUMIF('Calcul'!$B$2:$B$85,1,'Calcul'!$H$2:$H$85) | D14: =(SUMIF('Calcul'!$B$2:$B$85,2,'Calcul'!$R$2:$R$85)-MAX(0,SUMIF('Calcul'!$B$2:$B$85,2,'Calcul'!$R$2:$R$85))*'Hypothèses'!$C$54)/SUMIF('Calcul'!$B$2:$B$85,2,'Calcul'!$H$2:$H$85) | E14: =(SUMIF('Calcul'!$B$2:$B$85,3,'Calcul'!$R$2:$R$85)-MAX(0,SUMIF('Calcul'!$B$2:$B$85,3,'Calcul'!$R$2:$R$85))*'Hypothèses'!$C$54)/SUMIF('Calcul'!$B$2:$B$85,3,'Calcul'!$H$2:$H$85) | F14: =(SUMIF('Calcul'!$B$2:$B$85,4,'Calcul'!$R$2:$R$85)-MAX(0,SUMIF('Calcul'!$B$2:$B$85,4,'Calcul'!$R$2:$R$85))*'Hypothèses'!$C$54)/SUMIF('Calcul'!$B$2:$B$85,4,'Calcul'!$H$2:$H$85) | G14: =(SUMIF('Calcul'!$B$2:$B$85,5,'Calcul'!$R$2:$R$85)-MAX(0,SUMIF('Calcul'!$B$2:$B$85,5,'Calcul'!$R$2:$R$85))*'Hypothèses'!$C$54)/SUMIF('Calcul'!$B$2:$B$85,5,'Calcul'!$H$2:$H$85) | H14: =(SUMIF('Calcul'!$B$2:$B$85,6,'Calcul'!$R$2:$R$85)-MAX(0,SUMIF('Calcul'!$B$2:$B$85,6,'Calcul'!$R$2:$R$85))*'Hypothèses'!$C$54)/SUMIF('Calcul'!$B$2:$B$85,6,'Calcul'!$H$2:$H$85) | I14: =(SUMIF('Calcul'!$B$2:$B$85,7,'Calcul'!$R$2:$R$85)-MAX(0,SUMIF('Calcul'!$B$2:$B$85,7,'Calcul'!$R$2:$R$85))*'Hypothèses'!$C$54)/SUMIF('Calcul'!$B$2:$B$85,7,'Calcul'!$H$2:$H$85)
B15: COUVERTURE DU SERVICE LEASING (clé bailleur)
B16: Engagements leasing (loyers machines + véhicule) | C16: =SUMIF('Calcul'!$B$2:$B$85,1,'Calcul'!$J$2:$J$85)+SUMIF('Calcul'!$B$2:$B$85,1,'Calcul'!$Q$2:$Q$85) | D16: =SUMIF('Calcul'!$B$2:$B$85,2,'Calcul'!$J$2:$J$85)+SUMIF('Calcul'!$B$2:$B$85,2,'Calcul'!$Q$2:$Q$85) | E16: =SUMIF('Calcul'!$B$2:$B$85,3,'Calcul'!$J$2:$J$85)+SUMIF('Calcul'!$B$2:$B$85,3,'Calcul'!$Q$2:$Q$85) | F16: =SUMIF('Calcul'!$B$2:$B$85,4,'Calcul'!$J$2:$J$85)+SUMIF('Calcul'!$B$2:$B$85,4,'Calcul'!$Q$2:$Q$85) | G16: =SUMIF('Calcul'!$B$2:$B$85,5,'Calcul'!$J$2:$J$85)+SUMIF('Calcul'!$B$2:$B$85,5,'Calcul'!$Q$2:$Q$85) | H16: =SUMIF('Calcul'!$B$2:$B$85,6,'Calcul'!$J$2:$J$85)+SUMIF('Calcul'!$B$2:$B$85,6,'Calcul'!$Q$2:$Q$85) | I16: =SUMIF('Calcul'!$B$2:$B$85,7,'Calcul'!$J$2:$J$85)+SUMIF('Calcul'!$B$2:$B$85,7,'Calcul'!$Q$2:$Q$85) | J16: =SUM(C16:I16)
B17: DSCR (EBITDA avant loyers / loyers) | C17: =(SUMIF('Calcul'!$B$2:$B$85,1,'Calcul'!$R$2:$R$85)+SUMIF('Calcul'!$B$2:$B$85,1,'Calcul'!$J$2:$J$85)+SUMIF('Calcul'!$B$2:$B$85,1,'Calcul'!$Q$2:$Q$85))/(SUMIF('Calcul'!$B$2:$B$85,1,'Calcul'!$J$2:$J$85)+SUMIF('Calcul'!$B$2:$B$85,1,'Calcul'!$Q$2:$Q$85)) | D17: =(SUMIF('Calcul'!$B$2:$B$85,2,'Calcul'!$R$2:$R$85)+SUMIF('Calcul'!$B$2:$B$85,2,'Calcul'!$J$2:$J$85)+SUMIF('Calcul'!$B$2:$B$85,2,'Calcul'!$Q$2:$Q$85))/(SUMIF('Calcul'!$B$2:$B$85,2,'Calcul'!$J$2:$J$85)+SUMIF('Calcul'!$B$2:$B$85,2,'Calcul'!$Q$2:$Q$85)) | E17: =(SUMIF('Calcul'!$B$2:$B$85,3,'Calcul'!$R$2:$R$85)+SUMIF('Calcul'!$B$2:$B$85,3,'Calcul'!$J$2:$J$85)+SUMIF('Calcul'!$B$2:$B$85,3,'Calcul'!$Q$2:$Q$85))/(SUMIF('Calcul'!$B$2:$B$85,3,'Calcul'!$J$2:$J$85)+SUMIF('Calcul'!$B$2:$B$85,3,'Calcul'!$Q$2:$Q$85)) | F17: =(SUMIF('Calcul'!$B$2:$B$85,4,'Calcul'!$R$2:$R$85)+SUMIF('Calcul'!$B$2:$B$85,4,'Calcul'!$J$2:$J$85)+SUMIF('Calcul'!$B$2:$B$85,4,'Calcul'!$Q$2:$Q$85))/(SUMIF('Calcul'!$B$2:$B$85,4,'Calcul'!$J$2:$J$85)+SUMIF('Calcul'!$B$2:$B$85,4,'Calcul'!$Q$2:$Q$85)) | G17: =(SUMIF('Calcul'!$B$2:$B$85,5,'Calcul'!$R$2:$R$85)+SUMIF('Calcul'!$B$2:$B$85,5,'Calcul'!$J$2:$J$85)+SUMIF('Calcul'!$B$2:$B$85,5,'Calcul'!$Q$2:$Q$85))/(SUMIF('Calcul'!$B$2:$B$85,5,'Calcul'!$J$2:$J$85)+SUMIF('Calcul'!$B$2:$B$85,5,'Calcul'!$Q$2:$Q$85)) | H17: =(SUMIF('Calcul'!$B$2:$B$85,6,'Calcul'!$R$2:$R$85)+SUMIF('Calcul'!$B$2:$B$85,6,'Calcul'!$J$2:$J$85)+SUMIF('Calcul'!$B$2:$B$85,6,'Calcul'!$Q$2:$Q$85))/(SUMIF('Calcul'!$B$2:$B$85,6,'Calcul'!$J$2:$J$85)+SUMIF('Calcul'!$B$2:$B$85,6,'Calcul'!$Q$2:$Q$85)) | I17: =(SUMIF('Calcul'!$B$2:$B$85,7,'Calcul'!$R$2:$R$85)+SUMIF('Calcul'!$B$2:$B$85,7,'Calcul'!$J$2:$J$85)+SUMIF('Calcul'!$B$2:$B$85,7,'Calcul'!$Q$2:$Q$85))/(SUMIF('Calcul'!$B$2:$B$85,7,'Calcul'!$J$2:$J$85)+SUMIF('Calcul'!$B$2:$B$85,7,'Calcul'!$Q$2:$Q$85)) | J17: =MIN(C17:I17)
B18: EBITDA / loyers de leasing | C18: =SUMIF('Calcul'!$B$2:$B$85,1,'Calcul'!$R$2:$R$85)/(SUMIF('Calcul'!$B$2:$B$85,1,'Calcul'!$J$2:$J$85)+SUMIF('Calcul'!$B$2:$B$85,1,'Calcul'!$Q$2:$Q$85)) | D18: =SUMIF('Calcul'!$B$2:$B$85,2,'Calcul'!$R$2:$R$85)/(SUMIF('Calcul'!$B$2:$B$85,2,'Calcul'!$J$2:$J$85)+SUMIF('Calcul'!$B$2:$B$85,2,'Calcul'!$Q$2:$Q$85)) | E18: =SUMIF('Calcul'!$B$2:$B$85,3,'Calcul'!$R$2:$R$85)/(SUMIF('Calcul'!$B$2:$B$85,3,'Calcul'!$J$2:$J$85)+SUMIF('Calcul'!$B$2:$B$85,3,'Calcul'!$Q$2:$Q$85)) | F18: =SUMIF('Calcul'!$B$2:$B$85,4,'Calcul'!$R$2:$R$85)/(SUMIF('Calcul'!$B$2:$B$85,4,'Calcul'!$J$2:$J$85)+SUMIF('Calcul'!$B$2:$B$85,4,'Calcul'!$Q$2:$Q$85)) | G18: =SUMIF('Calcul'!$B$2:$B$85,5,'Calcul'!$R$2:$R$85)/(SUMIF('Calcul'!$B$2:$B$85,5,'Calcul'!$J$2:$J$85)+SUMIF('Calcul'!$B$2:$B$85,5,'Calcul'!$Q$2:$Q$85)) | H18: =SUMIF('Calcul'!$B$2:$B$85,6,'Calcul'!$R$2:$R$85)/(SUMIF('Calcul'!$B$2:$B$85,6,'Calcul'!$J$2:$J$85)+SUMIF('Calcul'!$B$2:$B$85,6,'Calcul'!$Q$2:$Q$85)) | I18: =SUMIF('Calcul'!$B$2:$B$85,7,'Calcul'!$R$2:$R$85)/(SUMIF('Calcul'!$B$2:$B$85,7,'Calcul'!$J$2:$J$85)+SUMIF('Calcul'!$B$2:$B$85,7,'Calcul'!$Q$2:$Q$85))
B19: STRUCTURE & RENTABILITÉ
B20: Capitaux propres | C20: =('Hypothèses'!$C$55+(1-'Hypothèses'!$C$56)*((SUMIF('Calcul'!$B$2:$B$85,1,'Calcul'!$R$2:$R$85)-MAX(0,SUMIF('Calcul'!$B$2:$B$85,1,'Calcul'!$R$2:$R$85))*'Hypothèses'!$C$54))) | D20: =('Hypothèses'!$C$55+(1-'Hypothèses'!$C$56)*((SUMIF('Calcul'!$B$2:$B$85,1,'Calcul'!$R$2:$R$85)-MAX(0,SUMIF('Calcul'!$B$2:$B$85,1,'Calcul'!$R$2:$R$85))*'Hypothèses'!$C$54)+(SUMIF('Calcul'!$B$2:$B$85,2,'Calcul'!$R$2:$R$85)-MAX(0,SUMIF('Calcul'!$B$2:$B$85,2,'Calcul'!$R$2:$R$85))*'Hypothèses'!$C$54))) | E20: =('Hypothèses'!$C$55+(1-'Hypothèses'!$C$56)*((SUMIF('Calcul'!$B$2:$B$85,1,'Calcul'!$R$2:$R$85)-MAX(0,SUMIF('Calcul'!$B$2:$B$85,1,'Calcul'!$R$2:$R$85))*'Hypothèses'!$C$54)+(SUMIF('Calcul'!$B$2:$B$85,2,'Calcul'!$R$2:$R$85)-MAX(0,SUMIF('Calcul'!$B$2:$B$85,2,'Calcul'!$R$2:$R$85))*'Hypothèses'!$C$54)+(SUMIF('Calcul'!$B$2:$B$85,3,'Calcul'!$R$2:$R$85)-MAX(0,SUMIF('Calcul'!$B$2:$B$85,3,'Calcul'!$R$2:$R$85))*'Hypothèses'!$C$54))) | F20: =('Hypothèses'!$C$55+(1-'Hypothèses'!$C$56)*((SUMIF('Calcul'!$B$2:$B$85,1,'Calcul'!$R$2:$R$85)-MAX(0,SUMIF('Calcul'!$B$2:$B$85,1,'Calcul'!$R$2:$R$85))*'Hypothèses'!$C$54)+(SUMIF('Calcul'!$B$2:$B$85,2,'Calcul'!$R$2:$R$85)-MAX(0,SUMIF('Calcul'!$B$2:$B$85,2,'Calcul'!$R$2:$R$85))*'Hypothèses'!$C$54)+(SUMIF('Calcul'!$B$2:$B$85,3,'Calcul'!$R$2:$R$85)-MAX(0,SUMIF('Calcul'!$B$2:$B$85,3,'Calcul'!$R$2:$R$85))*'Hypothèses'!$C$54)+(SUMIF('Calcul'!$B$2:$B$85,4,'Calcul'!$R$2:$R$85)-MAX(0,SUMIF('Calcul'!$B$2:$B$85,4,'Calcul'!$R$2:$R$85))*'Hypothèses'!$C$54))) | G20: =('Hypothèses'!$C$55+(1-'Hypothèses'!$C$56)*((SUMIF('Calcul'!$B$2:$B$85,1,'Calcul'!$R$2:$R$85)-MAX(0,SUMIF('Calcul'!$B$2:$B$85,1,'Calcul'!$R$2:$R$85))*'Hypothèses'!$C$54)+(SUMIF('Calcul'!$B$2:$B$85,2,'Calcul'!$R$2:$R$85)-MAX(0,SUMIF('Calcul'!$B$2:$B$85,2,'Calcul'!$R$2:$R$85))*'Hypothèses'!$C$54)+(SUMIF('Calcul'!$B$2:$B$85,3,'Calcul'!$R$2:$R$85)-MAX(0,SUMIF('Calcul'!$B$2:$B$85,3,'Calcul'!$R$2:$R$85))*'Hypothèses'!$C$54)+(SUMIF('Calcul'!$B$2:$B$85,4,'Calcul'!$R$2:$R$85)-MAX(0,SUMIF('Calcul'!$B$2:$B$85,4,'Calcul'!$R$2:$R$85))*'Hypothèses'!$C$54)+(SUMIF('Calcul'!$B$2:$B$85,5,'Calcul'!$R$2:$R$85)-MAX(0,SUMIF('Calcul'!$B$2:$B$85,5,'Calcul'!$R$2:$R$85))*'Hypothèses'!$C$54))) | H20: =('Hypothèses'!$C$55+(1-'Hypothèses'!$C$56)*((SUMIF('Calcul'!$B$2:$B$85,1,'Calcul'!$R$2:$R$85)-MAX(0,SUMIF('Calcul'!$B$2:$B$85,1,'Calcul'!$R$2:$R$85))*'Hypothèses'!$C$54)+(SUMIF('Calcul'!$B$2:$B$85,2,'Calcul'!$R$2:$R$85)-MAX(0,SUMIF('Calcul'!$B$2:$B$85,2,'Calcul'!$R$2:$R$85))*'Hypothèses'!$C$54)+(SUMIF('Calcul'!$B$2:$B$85,3,'Calcul'!$R$2:$R$85)-MAX(0,SUMIF('Calcul'!$B$2:$B$85,3,'Calcul'!$R$2:$R$85))*'Hypothèses'!$C$54)+(SUMIF('Calcul'!$B$2:$B$85,4,'Calcul'!$R$2:$R$85)-MAX(0,SUMIF('Calcul'!$B$2:$B$85,4,'Calcul'!$R$2:$R$85))*'Hypothèses'!$C$54)+(SUMIF('Calcul'!$B$2:$B$85,5,'Calcul'!$R$2:$R$85)-MAX(0,SUMIF('Calcul'!$B$2:$B$85,5,'Calcul'!$R$2:$R$85))*'Hypothèses'!$C$54)+(SUMIF('Calcul'!$B$2:$B$85,6,'Calcul'!$R$2:$R$85)-MAX(0,SUMIF('Calcul'!$B$2:$B$85,6,'Calcul'!$R$2:$R$85))*'Hypothèses'!$C$54))) | I20: =('Hypothèses'!$C$55+(1-'Hypothèses'!$C$56)*((SUMIF('Calcul'!$B$2:$B$85,1,'Calcul'!$R$2:$R$85)-MAX(0,SUMIF('Calcul'!$B$2:$B$85,1,'Calcul'!$R$2:$R$85))*'Hypothèses'!$C$54)+(SUMIF('Calcul'!$B$2:$B$85,2,'Calcul'!$R$2:$R$85)-MAX(0,SUMIF('Calcul'!$B$2:$B$85,2,'Calcul'!$R$2:$R$85))*'Hypothèses'!$C$54)+(SUMIF('Calcul'!$B$2:$B$85,3,'Calcul'!$R$2:$R$85)-MAX(0,SUMIF('Calcul'!$B$2:$B$85,3,'Calcul'!$R$2:$R$85))*'Hypothèses'!$C$54)+(SUMIF('Calcul'!$B$2:$B$85,4,'Calcul'!$R$2:$R$85)-MAX(0,SUMIF('Calcul'!$B$2:$B$85,4,'Calcul'!$R$2:$R$85))*'Hypothèses'!$C$54)+(SUMIF('Calcul'!$B$2:$B$85,5,'Calcul'!$R$2:$R$85)-MAX(0,SUMIF('Calcul'!$B$2:$B$85,5,'Calcul'!$R$2:$R$85))*'Hypothèses'!$C$54)+(SUMIF('Calcul'!$B$2:$B$85,6,'Calcul'!$R$2:$R$85)-MAX(0,SUMIF('Calcul'!$B$2:$B$85,6,'Calcul'!$R$2:$R$85))*'Hypothèses'!$C$54)+(SUMIF('Calcul'!$B$2:$B$85,7,'Calcul'!$R$2:$R$85)-MAX(0,SUMIF('Calcul'!$B$2:$B$85,7,'Calcul'!$R$2:$R$85))*'Hypothèses'!$C$54)))
B21: Dette financière bancaire | C21: =0 | D21: =0 | E21: =0 | F21: =0 | G21: =0 | H21: =0 | I21: =0
B22: Gearing (dette / capitaux propres) | C22: =0 | D22: =0 | E22: =0 | F22: =0 | G22: =0 | H22: =0 | I22: =0
B23: Trésorerie nette de clôture | C23: ='Calcul'!$T$13 | D23: ='Calcul'!$T$25-'Hypothèses'!$C$56*((SUMIF('Calcul'!$B$2:$B$85,1,'Calcul'!$R$2:$R$85)-MAX(0,SUMIF('Calcul'!$B$2:$B$85,1,'Calcul'!$R$2:$R$85))*'Hypothèses'!$C$54)) | E23: ='Calcul'!$T$37-'Hypothèses'!$C$56*((SUMIF('Calcul'!$B$2:$B$85,1,'Calcul'!$R$2:$R$85)-MAX(0,SUMIF('Calcul'!$B$2:$B$85,1,'Calcul'!$R$2:$R$85))*'Hypothèses'!$C$54)+(SUMIF('Calcul'!$B$2:$B$85,2,'Calcul'!$R$2:$R$85)-MAX(0,SUMIF('Calcul'!$B$2:$B$85,2,'Calcul'!$R$2:$R$85))*'Hypothèses'!$C$54)) | F23: ='Calcul'!$T$49-'Hypothèses'!$C$56*((SUMIF('Calcul'!$B$2:$B$85,1,'Calcul'!$R$2:$R$85)-MAX(0,SUMIF('Calcul'!$B$2:$B$85,1,'Calcul'!$R$2:$R$85))*'Hypothèses'!$C$54)+(SUMIF('Calcul'!$B$2:$B$85,2,'Calcul'!$R$2:$R$85)-MAX(0,SUMIF('Calcul'!$B$2:$B$85,2,'Calcul'!$R$2:$R$85))*'Hypothèses'!$C$54)+(SUMIF('Calcul'!$B$2:$B$85,3,'Calcul'!$R$2:$R$85)-MAX(0,SUMIF('Calcul'!$B$2:$B$85,3,'Calcul'!$R$2:$R$85))*'Hypothèses'!$C$54)) | G23: ='Calcul'!$T$61-'Hypothèses'!$C$56*((SUMIF('Calcul'!$B$2:$B$85,1,'Calcul'!$R$2:$R$85)-MAX(0,SUMIF('Calcul'!$B$2:$B$85,1,'Calcul'!$R$2:$R$85))*'Hypothèses'!$C$54)+(SUMIF('Calcul'!$B$2:$B$85,2,'Calcul'!$R$2:$R$85)-MAX(0,SUMIF('Calcul'!$B$2:$B$85,2,'Calcul'!$R$2:$R$85))*'Hypothèses'!$C$54)+(SUMIF('Calcul'!$B$2:$B$85,3,'Calcul'!$R$2:$R$85)-MAX(0,SUMIF('Calcul'!$B$2:$B$85,3,'Calcul'!$R$2:$R$85))*'Hypothèses'!$C$54)+(SUMIF('Calcul'!$B$2:$B$85,4,'Calcul'!$R$2:$R$85)-MAX(0,SUMIF('Calcul'!$B$2:$B$85,4,'Calcul'!$R$2:$R$85))*'Hypothèses'!$C$54)) | H23: ='Calcul'!$T$73-'Hypothèses'!$C$56*((SUMIF('Calcul'!$B$2:$B$85,1,'Calcul'!$R$2:$R$85)-MAX(0,SUMIF('Calcul'!$B$2:$B$85,1,'Calcul'!$R$2:$R$85))*'Hypothèses'!$C$54)+(SUMIF('Calcul'!$B$2:$B$85,2,'Calcul'!$R$2:$R$85)-MAX(0,SUMIF('Calcul'!$B$2:$B$85,2,'Calcul'!$R$2:$R$85))*'Hypothèses'!$C$54)+(SUMIF('Calcul'!$B$2:$B$85,3,'Calcul'!$R$2:$R$85)-MAX(0,SUMIF('Calcul'!$B$2:$B$85,3,'Calcul'!$R$2:$R$85))*'Hypothèses'!$C$54)+(SUMIF('Calcul'!$B$2:$B$85,4,'Calcul'!$R$2:$R$85)-MAX(0,SUMIF('Calcul'!$B$2:$B$85,4,'Calcul'!$R$2:$R$85))*'Hypothèses'!$C$54)+(SUMIF('Calcul'!$B$2:$B$85,5,'Calcul'!$R$2:$R$85)-MAX(0,SUMIF('Calcul'!$B$2:$B$85,5,'Calcul'!$R$2:$R$85))*'Hypothèses'!$C$54)) | I23: ='Calcul'!$T$85-'Hypothèses'!$C$56*((SUMIF('Calcul'!$B$2:$B$85,1,'Calcul'!$R$2:$R$85)-MAX(0,SUMIF('Calcul'!$B$2:$B$85,1,'Calcul'!$R$2:$R$85))*'Hypothèses'!$C$54)+(SUMIF('Calcul'!$B$2:$B$85,2,'Calcul'!$R$2:$R$85)-MAX(0,SUMIF('Calcul'!$B$2:$B$85,2,'Calcul'!$R$2:$R$85))*'Hypothèses'!$C$54)+(SUMIF('Calcul'!$B$2:$B$85,3,'Calcul'!$R$2:$R$85)-MAX(0,SUMIF('Calcul'!$B$2:$B$85,3,'Calcul'!$R$2:$R$85))*'Hypothèses'!$C$54)+(SUMIF('Calcul'!$B$2:$B$85,4,'Calcul'!$R$2:$R$85)-MAX(0,SUMIF('Calcul'!$B$2:$B$85,4,'Calcul'!$R$2:$R$85))*'Hypothèses'!$C$54)+(SUMIF('Calcul'!$B$2:$B$85,5,'Calcul'!$R$2:$R$85)-MAX(0,SUMIF('Calcul'!$B$2:$B$85,5,'Calcul'!$R$2:$R$85))*'Hypothèses'!$C$54)+(SUMIF('Calcul'!$B$2:$B$85,6,'Calcul'!$R$2:$R$85)-MAX(0,SUMIF('Calcul'!$B$2:$B$85,6,'Calcul'!$R$2:$R$85))*'Hypothèses'!$C$54))
B24: ROE (résultat net / capitaux propres) | C24: =(SUMIF('Calcul'!$B$2:$B$85,1,'Calcul'!$R$2:$R$85)-MAX(0,SUMIF('Calcul'!$B$2:$B$85,1,'Calcul'!$R$2:$R$85))*'Hypothèses'!$C$54)/('Hypothèses'!$C$55+(1-'Hypothèses'!$C$56)*((SUMIF('Calcul'!$B$2:$B$85,1,'Calcul'!$R$2:$R$85)-MAX(0,SUMIF('Calcul'!$B$2:$B$85,1,'Calcul'!$R$2:$R$85))*'Hypothèses'!$C$54))) | D24: =(SUMIF('Calcul'!$B$2:$B$85,2,'Calcul'!$R$2:$R$85)-MAX(0,SUMIF('Calcul'!$B$2:$B$85,2,'Calcul'!$R$2:$R$85))*'Hypothèses'!$C$54)/('Hypothèses'!$C$55+(1-'Hypothèses'!$C$56)*((SUMIF('Calcul'!$B$2:$B$85,1,'Calcul'!$R$2:$R$85)-MAX(0,SUMIF('Calcul'!$B$2:$B$85,1,'Calcul'!$R$2:$R$85))*'Hypothèses'!$C$54)+(SUMIF('Calcul'!$B$2:$B$85,2,'Calcul'!$R$2:$R$85)-MAX(0,SUMIF('Calcul'!$B$2:$B$85,2,'Calcul'!$R$2:$R$85))*'Hypothèses'!$C$54))) | E24: =(SUMIF('Calcul'!$B$2:$B$85,3,'Calcul'!$R$2:$R$85)-MAX(0,SUMIF('Calcul'!$B$2:$B$85,3,'Calcul'!$R$2:$R$85))*'Hypothèses'!$C$54)/('Hypothèses'!$C$55+(1-'Hypothèses'!$C$56)*((SUMIF('Calcul'!$B$2:$B$85,1,'Calcul'!$R$2:$R$85)-MAX(0,SUMIF('Calcul'!$B$2:$B$85,1,'Calcul'!$R$2:$R$85))*'Hypothèses'!$C$54)+(SUMIF('Calcul'!$B$2:$B$85,2,'Calcul'!$R$2:$R$85)-MAX(0,SUMIF('Calcul'!$B$2:$B$85,2,'Calcul'!$R$2:$R$85))*'Hypothèses'!$C$54)+(SUMIF('Calcul'!$B$2:$B$85,3,'Calcul'!$R$2:$R$85)-MAX(0,SUMIF('Calcul'!$B$2:$B$85,3,'Calcul'!$R$2:$R$85))*'Hypothèses'!$C$54))) | F24: =(SUMIF('Calcul'!$B$2:$B$85,4,'Calcul'!$R$2:$R$85)-MAX(0,SUMIF('Calcul'!$B$2:$B$85,4,'Calcul'!$R$2:$R$85))*'Hypothèses'!$C$54)/('Hypothèses'!$C$55+(1-'Hypothèses'!$C$56)*((SUMIF('Calcul'!$B$2:$B$85,1,'Calcul'!$R$2:$R$85)-MAX(0,SUMIF('Calcul'!$B$2:$B$85,1,'Calcul'!$R$2:$R$85))*'Hypothèses'!$C$54)+(SUMIF('Calcul'!$B$2:$B$85,2,'Calcul'!$R$2:$R$85)-MAX(0,SUMIF('Calcul'!$B$2:$B$85,2,'Calcul'!$R$2:$R$85))*'Hypothèses'!$C$54)+(SUMIF('Calcul'!$B$2:$B$85,3,'Calcul'!$R$2:$R$85)-MAX(0,SUMIF('Calcul'!$B$2:$B$85,3,'Calcul'!$R$2:$R$85))*'Hypothèses'!$C$54)+(SUMIF('Calcul'!$B$2:$B$85,4,'Calcul'!$R$2:$R$85)-MAX(0,SUMIF('Calcul'!$B$2:$B$85,4,'Calcul'!$R$2:$R$85))*'Hypothèses'!$C$54))) | G24: =(SUMIF('Calcul'!$B$2:$B$85,5,'Calcul'!$R$2:$R$85)-MAX(0,SUMIF('Calcul'!$B$2:$B$85,5,'Calcul'!$R$2:$R$85))*'Hypothèses'!$C$54)/('Hypothèses'!$C$55+(1-'Hypothèses'!$C$56)*((SUMIF('Calcul'!$B$2:$B$85,1,'Calcul'!$R$2:$R$85)-MAX(0,SUMIF('Calcul'!$B$2:$B$85,1,'Calcul'!$R$2:$R$85))*'Hypothèses'!$C$54)+(SUMIF('Calcul'!$B$2:$B$85,2,'Calcul'!$R$2:$R$85)-MAX(0,SUMIF('Calcul'!$B$2:$B$85,2,'Calcul'!$R$2:$R$85))*'Hypothèses'!$C$54)+(SUMIF('Calcul'!$B$2:$B$85,3,'Calcul'!$R$2:$R$85)-MAX(0,SUMIF('Calcul'!$B$2:$B$85,3,'Calcul'!$R$2:$R$85))*'Hypothèses'!$C$54)+(SUMIF('Calcul'!$B$2:$B$85,4,'Calcul'!$R$2:$R$85)-MAX(0,SUMIF('Calcul'!$B$2:$B$85,4,'Calcul'!$R$2:$R$85))*'Hypothèses'!$C$54)+(SUMIF('Calcul'!$B$2:$B$85,5,'Calcul'!$R$2:$R$85)-MAX(0,SUMIF('Calcul'!$B$2:$B$85,5,'Calcul'!$R$2:$R$85))*'Hypothèses'!$C$54))) | H24: =(SUMIF('Calcul'!$B$2:$B$85,6,'Calcul'!$R$2:$R$85)-MAX(0,SUMIF('Calcul'!$B$2:$B$85,6,'Calcul'!$R$2:$R$85))*'Hypothèses'!$C$54)/('Hypothèses'!$C$55+(1-'Hypothèses'!$C$56)*((SUMIF('Calcul'!$B$2:$B$85,1,'Calcul'!$R$2:$R$85)-MAX(0,SUMIF('Calcul'!$B$2:$B$85,1,'Calcul'!$R$2:$R$85))*'Hypothèses'!$C$54)+(SUMIF('Calcul'!$B$2:$B$85,2,'Calcul'!$R$2:$R$85)-MAX(0,SUMIF('Calcul'!$B$2:$B$85,2,'Calcul'!$R$2:$R$85))*'Hypothèses'!$C$54)+(SUMIF('Calcul'!$B$2:$B$85,3,'Calcul'!$R$2:$R$85)-MAX(0,SUMIF('Calcul'!$B$2:$B$85,3,'Calcul'!$R$2:$R$85))*'Hypothèses'!$C$54)+(SUMIF('Calcul'!$B$2:$B$85,4,'Calcul'!$R$2:$R$85)-MAX(0,SUMIF('Calcul'!$B$2:$B$85,4,'Calcul'!$R$2:$R$85))*'Hypothèses'!$C$54)+(SUMIF('Calcul'!$B$2:$B$85,5,'Calcul'!$R$2:$R$85)-MAX(0,SUMIF('Calcul'!$B$2:$B$85,5,'Calcul'!$R$2:$R$85))*'Hypothèses'!$C$54)+(SUMIF('Calcul'!$B$2:$B$85,6,'Calcul'!$R$2:$R$85)-MAX(0,SUMIF('Calcul'!$B$2:$B$85,6,'Calcul'!$R$2:$R$85))*'Hypothèses'!$C$54))) | I24: =(SUMIF('Calcul'!$B$2:$B$85,7,'Calcul'!$R$2:$R$85)-MAX(0,SUMIF('Calcul'!$B$2:$B$85,7,'Calcul'!$R$2:$R$85))*'Hypothèses'!$C$54)/('Hypothèses'!$C$55+(1-'Hypothèses'!$C$56)*((SUMIF('Calcul'!$B$2:$B$85,1,'Calcul'!$R$2:$R$85)-MAX(0,SUMIF('Calcul'!$B$2:$B$85,1,'Calcul'!$R$2:$R$85))*'Hypothèses'!$C$54)+(SUMIF('Calcul'!$B$2:$B$85,2,'Calcul'!$R$2:$R$85)-MAX(0,SUMIF('Calcul'!$B$2:$B$85,2,'Calcul'!$R$2:$R$85))*'Hypothèses'!$C$54)+(SUMIF('Calcul'!$B$2:$B$85,3,'Calcul'!$R$2:$R$85)-MAX(0,SUMIF('Calcul'!$B$2:$B$85,3,'Calcul'!$R$2:$R$85))*'Hypothèses'!$C$54)+(SUMIF('Calcul'!$B$2:$B$85,4,'Calcul'!$R$2:$R$85)-MAX(0,SUMIF('Calcul'!$B$2:$B$85,4,'Calcul'!$R$2:$R$85))*'Hypothèses'!$C$54)+(SUMIF('Calcul'!$B$2:$B$85,5,'Calcul'!$R$2:$R$85)-MAX(0,SUMIF('Calcul'!$B$2:$B$85,5,'Calcul'!$R$2:$R$85))*'Hypothèses'!$C$54)+(SUMIF('Calcul'!$B$2:$B$85,6,'Calcul'!$R$2:$R$85)-MAX(0,SUMIF('Calcul'!$B$2:$B$85,6,'Calcul'!$R$2:$R$85))*'Hypothèses'!$C$54)+(SUMIF('Calcul'!$B$2:$B$85,7,'Calcul'!$R$2:$R$85)-MAX(0,SUMIF('Calcul'!$B$2:$B$85,7,'Calcul'!$R$2:$R$85))*'Hypothèses'!$C$54)))
B25: Rentabilité du capital social | C25: =(SUMIF('Calcul'!$B$2:$B$85,1,'Calcul'!$R$2:$R$85)-MAX(0,SUMIF('Calcul'!$B$2:$B$85,1,'Calcul'!$R$2:$R$85))*'Hypothèses'!$C$54)/'Hypothèses'!$C$55 | D25: =(SUMIF('Calcul'!$B$2:$B$85,2,'Calcul'!$R$2:$R$85)-MAX(0,SUMIF('Calcul'!$B$2:$B$85,2,'Calcul'!$R$2:$R$85))*'Hypothèses'!$C$54)/'Hypothèses'!$C$55 | E25: =(SUMIF('Calcul'!$B$2:$B$85,3,'Calcul'!$R$2:$R$85)-MAX(0,SUMIF('Calcul'!$B$2:$B$85,3,'Calcul'!$R$2:$R$85))*'Hypothèses'!$C$54)/'Hypothèses'!$C$55 | F25: =(SUMIF('Calcul'!$B$2:$B$85,4,'Calcul'!$R$2:$R$85)-MAX(0,SUMIF('Calcul'!$B$2:$B$85,4,'Calcul'!$R$2:$R$85))*'Hypothèses'!$C$54)/'Hypothèses'!$C$55 | G25: =(SUMIF('Calcul'!$B$2:$B$85,5,'Calcul'!$R$2:$R$85)-MAX(0,SUMIF('Calcul'!$B$2:$B$85,5,'Calcul'!$R$2:$R$85))*'Hypothèses'!$C$54)/'Hypothèses'!$C$55 | H25: =(SUMIF('Calcul'!$B$2:$B$85,6,'Calcul'!$R$2:$R$85)-MAX(0,SUMIF('Calcul'!$B$2:$B$85,6,'Calcul'!$R$2:$R$85))*'Hypothèses'!$C$54)/'Hypothèses'!$C$55 | I25: =(SUMIF('Calcul'!$B$2:$B$85,7,'Calcul'!$R$2:$R$85)-MAX(0,SUMIF('Calcul'!$B$2:$B$85,7,'Calcul'!$R$2:$R$85))*'Hypothèses'!$C$54)/'Hypothèses'!$C$55

Sheet Capacité leasing
B1: Capacité de remboursement du leasing
B2: L'indicateur clé pour le bailleur : les loyers sont couverts plusieurs fois par les flux d'exploitation.
B4: AU NIVEAU D'UNE MACHINE (An 1)
B5: Revenu HCTECH / machine / an (part 60 %) | C5: ='Hypothèses'!$C$19*365*'Hypothèses'!$C$20*'Hypothèses'!$C$22
B6: Loyer de leasing / machine / an | C6: ='Hypothèses'!$C$13
B7: Couverture du loyer par le revenu | C7: =C5/C6 | D7: → chaque machine couvre largement son propre loyer
B9: AU NIVEAU DE LA SOCIÉTÉ (par année)
C10: An 1 | D10: An 2 | E10: An 3 | F10: An 4 | G10: An 5 | H10: An 6 | I10: An 7 | J10: Total 7 ans
B11: Loyers leasing machines | C11: =SUMIF('Calcul'!$B$2:$B$85,1,'Calcul'!$J$2:$J$85) | D11: =SUMIF('Calcul'!$B$2:$B$85,2,'Calcul'!$J$2:$J$85) | E11: =SUMIF('Calcul'!$B$2:$B$85,3,'Calcul'!$J$2:$J$85) | F11: =SUMIF('Calcul'!$B$2:$B$85,4,'Calcul'!$J$2:$J$85) | G11: =SUMIF('Calcul'!$B$2:$B$85,5,'Calcul'!$J$2:$J$85) | H11: =SUMIF('Calcul'!$B$2:$B$85,6,'Calcul'!$J$2:$J$85) | I11: =SUMIF('Calcul'!$B$2:$B$85,7,'Calcul'!$J$2:$J$85) | J11: =SUM(C11:I11)
B12: Loyer leasing véhicule | C12: =SUMIF('Calcul'!$B$2:$B$85,1,'Calcul'!$Q$2:$Q$85) | D12: =SUMIF('Calcul'!$B$2:$B$85,2,'Calcul'!$Q$2:$Q$85) | E12: =SUMIF('Calcul'!$B$2:$B$85,3,'Calcul'!$Q$2:$Q$85) | F12: =SUMIF('Calcul'!$B$2:$B$85,4,'Calcul'!$Q$2:$Q$85) | G12: =SUMIF('Calcul'!$B$2:$B$85,5,'Calcul'!$Q$2:$Q$85) | H12: =SUMIF('Calcul'!$B$2:$B$85,6,'Calcul'!$Q$2:$Q$85) | I12: =SUMIF('Calcul'!$B$2:$B$85,7,'Calcul'!$Q$2:$Q$85) | J12: =SUM(C12:I12)
B13: Total engagements leasing | C13: =SUMIF('Calcul'!$B$2:$B$85,1,'Calcul'!$J$2:$J$85)+SUMIF('Calcul'!$B$2:$B$85,1,'Calcul'!$Q$2:$Q$85) | D13: =SUMIF('Calcul'!$B$2:$B$85,2,'Calcul'!$J$2:$J$85)+SUMIF('Calcul'!$B$2:$B$85,2,'Calcul'!$Q$2:$Q$85) | E13: =SUMIF('Calcul'!$B$2:$B$85,3,'Calcul'!$J$2:$J$85)+SUMIF('Calcul'!$B$2:$B$85,3,'Calcul'!$Q$2:$Q$85) | F13: =SUMIF('Calcul'!$B$2:$B$85,4,'Calcul'!$J$2:$J$85)+SUMIF('Calcul'!$B$2:$B$85,4,'Calcul'!$Q$2:$Q$85) | G13: =SUMIF('Calcul'!$B$2:$B$85,5,'Calcul'!$J$2:$J$85)+SUMIF('Calcul'!$B$2:$B$85,5,'Calcul'!$Q$2:$Q$85) | H13: =SUMIF('Calcul'!$B$2:$B$85,6,'Calcul'!$J$2:$J$85)+SUMIF('Calcul'!$B$2:$B$85,6,'Calcul'!$Q$2:$Q$85) | I13: =SUMIF('Calcul'!$B$2:$B$85,7,'Calcul'!$J$2:$J$85)+SUMIF('Calcul'!$B$2:$B$85,7,'Calcul'!$Q$2:$Q$85) | J13: =SUM(C13:I13)
B14: EBITDA avant loyers de leasing | C14: =SUMIF('Calcul'!$B$2:$B$85,1,'Calcul'!$R$2:$R$85)+SUMIF('Calcul'!$B$2:$B$85,1,'Calcul'!$J$2:$J$85)+SUMIF('Calcul'!$B$2:$B$85,1,'Calcul'!$Q$2:$Q$85) | D14: =SUMIF('Calcul'!$B$2:$B$85,2,'Calcul'!$R$2:$R$85)+SUMIF('Calcul'!$B$2:$B$85,2,'Calcul'!$J$2:$J$85)+SUMIF('Calcul'!$B$2:$B$85,2,'Calcul'!$Q$2:$Q$85) | E14: =SUMIF('Calcul'!$B$2:$B$85,3,'Calcul'!$R$2:$R$85)+SUMIF('Calcul'!$B$2:$B$85,3,'Calcul'!$J$2:$J$85)+SUMIF('Calcul'!$B$2:$B$85,3,'Calcul'!$Q$2:$Q$85) | F14: =SUMIF('Calcul'!$B$2:$B$85,4,'Calcul'!$R$2:$R$85)+SUMIF('Calcul'!$B$2:$B$85,4,'Calcul'!$J$2:$J$85)+SUMIF('Calcul'!$B$2:$B$85,4,'Calcul'!$Q$2:$Q$85) | G14: =SUMIF('Calcul'!$B$2:$B$85,5,'Calcul'!$R$2:$R$85)+SUMIF('Calcul'!$B$2:$B$85,5,'Calcul'!$J$2:$J$85)+SUMIF('Calcul'!$B$2:$B$85,5,'Calcul'!$Q$2:$Q$85) | H14: =SUMIF('Calcul'!$B$2:$B$85,6,'Calcul'!$R$2:$R$85)+SUMIF('Calcul'!$B$2:$B$85,6,'Calcul'!$J$2:$J$85)+SUMIF('Calcul'!$B$2:$B$85,6,'Calcul'!$Q$2:$Q$85) | I14: =SUMIF('Calcul'!$B$2:$B$85,7,'Calcul'!$R$2:$R$85)+SUMIF('Calcul'!$B$2:$B$85,7,'Calcul'!$J$2:$J$85)+SUMIF('Calcul'!$B$2:$B$85,7,'Calcul'!$Q$2:$Q$85) | J14: =SUM(C14:I14)
B15: Couverture du service leasing (DSCR) | C15: =(SUMIF('Calcul'!$B$2:$B$85,1,'Calcul'!$R$2:$R$85)+SUMIF('Calcul'!$B$2:$B$85,1,'Calcul'!$J$2:$J$85)+SUMIF('Calcul'!$B$2:$B$85,1,'Calcul'!$Q$2:$Q$85))/(SUMIF('Calcul'!$B$2:$B$85,1,'Calcul'!$J$2:$J$85)+SUMIF('Calcul'!$B$2:$B$85,1,'Calcul'!$Q$2:$Q$85)) | D15: =(SUMIF('Calcul'!$B$2:$B$85,2,'Calcul'!$R$2:$R$85)+SUMIF('Calcul'!$B$2:$B$85,2,'Calcul'!$J$2:$J$85)+SUMIF('Calcul'!$B$2:$B$85,2,'Calcul'!$Q$2:$Q$85))/(SUMIF('Calcul'!$B$2:$B$85,2,'Calcul'!$J$2:$J$85)+SUMIF('Calcul'!$B$2:$B$85,2,'Calcul'!$Q$2:$Q$85)) | E15: =(SUMIF('Calcul'!$B$2:$B$85,3,'Calcul'!$R$2:$R$85)+SUMIF('Calcul'!$B$2:$B$85,3,'Calcul'!$J$2:$J$85)+SUMIF('Calcul'!$B$2:$B$85,3,'Calcul'!$Q$2:$Q$85))/(SUMIF('Calcul'!$B$2:$B$85,3,'Calcul'!$J$2:$J$85)+SUMIF('Calcul'!$B$2:$B$85,3,'Calcul'!$Q$2:$Q$85)) | F15: =(SUMIF('Calcul'!$B$2:$B$85,4,'Calcul'!$R$2:$R$85)+SUMIF('Calcul'!$B$2:$B$85,4,'Calcul'!$J$2:$J$85)+SUMIF('Calcul'!$B$2:$B$85,4,'Calcul'!$Q$2:$Q$85))/(SUMIF('Calcul'!$B$2:$B$85,4,'Calcul'!$J$2:$J$85)+SUMIF('Calcul'!$B$2:$B$85,4,'Calcul'!$Q$2:$Q$85)) | G15: =(SUMIF('Calcul'!$B$2:$B$85,5,'Calcul'!$R$2:$R$85)+SUMIF('Calcul'!$B$2:$B$85,5,'Calcul'!$J$2:$J$85)+SUMIF('Calcul'!$B$2:$B$85,5,'Calcul'!$Q$2:$Q$85))/(SUMIF('Calcul'!$B$2:$B$85,5,'Calcul'!$J$2:$J$85)+SUMIF('Calcul'!$B$2:$B$85,5,'Calcul'!$Q$2:$Q$85)) | H15: =(SUMIF('Calcul'!$B$2:$B$85,6,'Calcul'!$R$2:$R$85)+SUMIF('Calcul'!$B$2:$B$85,6,'Calcul'!$J$2:$J$85)+SUMIF('Calcul'!$B$2:$B$85,6,'Calcul'!$Q$2:$Q$85))/(SUMIF('Calcul'!$B$2:$B$85,6,'Calcul'!$J$2:$J$85)+SUMIF('Calcul'!$B$2:$B$85,6,'Calcul'!$Q$2:$Q$85)) | I15: =(SUMIF('Calcul'!$B$2:$B$85,7,'Calcul'!$R$2:$R$85)+SUMIF('Calcul'!$B$2:$B$85,7,'Calcul'!$J$2:$J$85)+SUMIF('Calcul'!$B$2:$B$85,7,'Calcul'!$Q$2:$Q$85))/(SUMIF('Calcul'!$B$2:$B$85,7,'Calcul'!$J$2:$J$85)+SUMIF('Calcul'!$B$2:$B$85,7,'Calcul'!$Q$2:$Q$85)) | J15: =AVERAGE(C15:I15)
B17: DSCR minimum sur la période | C17: =MIN(C15:I15) | D17: Un DSCR > 1 signifie que l'exploitation couvre intégralement le service du leasing chaque année.

Sheet Dividendes
B1: Distribution & actionnariat
B2: Priorité à l'investisseur (capital + prime 20 % = 360 k), puis pro-rata. 30 % conservé en réserve.
C4: An 1 | D4: An 2 | E4: An 3 | F4: An 4 | G4: An 5 | H4: An 6 | I4: An 7 | J4: Total 7 ans
B5: Résultat net | C5: =(SUMIF('Calcul'!$B$2:$B$85,1,'Calcul'!$R$2:$R$85)-MAX(0,SUMIF('Calcul'!$B$2:$B$85,1,'Calcul'!$R$2:$R$85))*'Hypothèses'!$C$54) | D5: =(SUMIF('Calcul'!$B$2:$B$85,2,'Calcul'!$R$2:$R$85)-MAX(0,SUMIF('Calcul'!$B$2:$B$85,2,'Calcul'!$R$2:$R$85))*'Hypothèses'!$C$54) | E5: =(SUMIF('Calcul'!$B$2:$B$85,3,'Calcul'!$R$2:$R$85)-MAX(0,SUMIF('Calcul'!$B$2:$B$85,3,'Calcul'!$R$2:$R$85))*'Hypothèses'!$C$54) | F5: =(SUMIF('Calcul'!$B$2:$B$85,4,'Calcul'!$R$2:$R$85)-MAX(0,SUMIF('Calcul'!$B$2:$B$85,4,'Calcul'!$R$2:$R$85))*'Hypothèses'!$C$54) | G5: =(SUMIF('Calcul'!$B$2:$B$85,5,'Calcul'!$R$2:$R$85)-MAX(0,SUMIF('Calcul'!$B$2:$B$85,5,'Calcul'!$R$2:$R$85))*'Hypothèses'!$C$54) | H5: =(SUMIF('Calcul'!$B$2:$B$85,6,'Calcul'!$R$2:$R$85)-MAX(0,SUMIF('Calcul'!$B$2:$B$85,6,'Calcul'!$R$2:$R$85))*'Hypothèses'!$C$54) | I5: =(SUMIF('Calcul'!$B$2:$B$85,7,'Calcul'!$R$2:$R$85)-MAX(0,SUMIF('Calcul'!$B$2:$B$85,7,'Calcul'!$R$2:$R$85))*'Hypothèses'!$C$54) | J5: =SUM(C5:I5)
B6: Enveloppe distribuable (payout 70 %) | C6: ='Hypothèses'!$C$56*(SUMIF('Calcul'!$B$2:$B$85,1,'Calcul'!$R$2:$R$85)-MAX(0,SUMIF('Calcul'!$B$2:$B$85,1,'Calcul'!$R$2:$R$85))*'Hypothèses'!$C$54) | D6: ='Hypothèses'!$C$56*(SUMIF('Calcul'!$B$2:$B$85,2,'Calcul'!$R$2:$R$85)-MAX(0,SUMIF('Calcul'!$B$2:$B$85,2,'Calcul'!$R$2:$R$85))*'Hypothèses'!$C$54) | E6: ='Hypothèses'!$C$56*(SUMIF('Calcul'!$B$2:$B$85,3,'Calcul'!$R$2:$R$85)-MAX(0,SUMIF('Calcul'!$B$2:$B$85,3,'Calcul'!$R$2:$R$85))*'Hypothèses'!$C$54) | F6: ='Hypothèses'!$C$56*(SUMIF('Calcul'!$B$2:$B$85,4,'Calcul'!$R$2:$R$85)-MAX(0,SUMIF('Calcul'!$B$2:$B$85,4,'Calcul'!$R$2:$R$85))*'Hypothèses'!$C$54) | G6: ='Hypothèses'!$C$56*(SUMIF('Calcul'!$B$2:$B$85,5,'Calcul'!$R$2:$R$85)-MAX(0,SUMIF('Calcul'!$B$2:$B$85,5,'Calcul'!$R$2:$R$85))*'Hypothèses'!$C$54) | H6: ='Hypothèses'!$C$56*(SUMIF('Calcul'!$B$2:$B$85,6,'Calcul'!$R$2:$R$85)-MAX(0,SUMIF('Calcul'!$B$2:$B$85,6,'Calcul'!$R$2:$R$85))*'Hypothèses'!$C$54) | I6: ='Hypothèses'!$C$56*(SUMIF('Calcul'!$B$2:$B$85,7,'Calcul'!$R$2:$R$85)-MAX(0,SUMIF('Calcul'!$B$2:$B$85,7,'Calcul'!$R$2:$R$85))*'Hypothèses'!$C$54) | J6: =SUM(C6:I6)
B7: Récupération prioritaire Nessim | C7: =MIN('Hypothèses'!$C$56*(SUMIF('Calcul'!$B$2:$B$85,1,'Calcul'!$R$2:$R$85)-MAX(0,SUMIF('Calcul'!$B$2:$B$85,1,'Calcul'!$R$2:$R$85))*'Hypothèses'!$C$54),MAX(0,'Hypothèses'!$C$58-(0))) | D7: =MIN('Hypothèses'!$C$56*(SUMIF('Calcul'!$B$2:$B$85,2,'Calcul'!$R$2:$R$85)-MAX(0,SUMIF('Calcul'!$B$2:$B$85,2,'Calcul'!$R$2:$R$85))*'Hypothèses'!$C$54),MAX(0,'Hypothèses'!$C$58-('Hypothèses'!$C$56*(SUMIF('Calcul'!$B$2:$B$85,1,'Calcul'!$R$2:$R$85)-MAX(0,SUMIF('Calcul'!$B$2:$B$85,1,'Calcul'!$R$2:$R$85))*'Hypothèses'!$C$54)))) | E7: =MIN('Hypothèses'!$C$56*(SUMIF('Calcul'!$B$2:$B$85,3,'Calcul'!$R$2:$R$85)-MAX(0,SUMIF('Calcul'!$B$2:$B$85,3,'Calcul'!$R$2:$R$85))*'Hypothèses'!$C$54),MAX(0,'Hypothèses'!$C$58-('Hypothèses'!$C$56*(SUMIF('Calcul'!$B$2:$B$85,1,'Calcul'!$R$2:$R$85)-MAX(0,SUMIF('Calcul'!$B$2:$B$85,1,'Calcul'!$R$2:$R$85))*'Hypothèses'!$C$54)+'Hypothèses'!$C$56*(SUMIF('Calcul'!$B$2:$B$85,2,'Calcul'!$R$2:$R$85)-MAX(0,SUMIF('Calcul'!$B$2:$B$85,2,'Calcul'!$R$2:$R$85))*'Hypothèses'!$C$54)))) | F7: =MIN('Hypothèses'!$C$56*(SUMIF('Calcul'!$B$2:$B$85,4,'Calcul'!$R$2:$R$85)-MAX(0,SUMIF('Calcul'!$B$2:$B$85,4,'Calcul'!$R$2:$R$85))*'Hypothèses'!$C$54),MAX(0,'Hypothèses'!$C$58-('Hypothèses'!$C$56*(SUMIF('Calcul'!$B$2:$B$85,1,'Calcul'!$R$2:$R$85)-MAX(0,SUMIF('Calcul'!$B$2:$B$85,1,'Calcul'!$R$2:$R$85))*'Hypothèses'!$C$54)+'Hypothèses'!$C$56*(SUMIF('Calcul'!$B$2:$B$85,2,'Calcul'!$R$2:$R$85)-MAX(0,SUMIF('Calcul'!$B$2:$B$85,2,'Calcul'!$R$2:$R$85))*'Hypothèses'!$C$54)+'Hypothèses'!$C$56*(SUMIF('Calcul'!$B$2:$B$85,3,'Calcul'!$R$2:$R$85)-MAX(0,SUMIF('Calcul'!$B$2:$B$85,3,'Calcul'!$R$2:$R$85))*'Hypothèses'!$C$54)))) | G7: =MIN('Hypothèses'!$C$56*(SUMIF('Calcul'!$B$2:$B$85,5,'Calcul'!$R$2:$R$85)-MAX(0,SUMIF('Calcul'!$B$2:$B$85,5,'Calcul'!$R$2:$R$85))*'Hypothèses'!$C$54),MAX(0,'Hypothèses'!$C$58-('Hypothèses'!$C$56*(SUMIF('Calcul'!$B$2:$B$85,1,'Calcul'!$R$2:$R$85)-MAX(0,SUMIF('Calcul'!$B$2:$B$85,1,'Calcul'!$R$2:$R$85))*'Hypothèses'!$C$54)+'Hypothèses'!$C$56*(SUMIF('Calcul'!$B$2:$B$85,2,'Calcul'!$R$2:$R$85)-MAX(0,SUMIF('Calcul'!$B$2:$B$85,2,'Calcul'!$R$2:$R$85))*'Hypothèses'!$C$54)+'Hypothèses'!$C$56*(SUMIF('Calcul'!$B$2:$B$85,3,'Calcul'!$R$2:$R$85)-MAX(0,SUMIF('Calcul'!$B$2:$B$85,3,'Calcul'!$R$2:$R$85))*'Hypothèses'!$C$54)+'Hypothèses'!$C$56*(SUMIF('Calcul'!$B$2:$B$85,4,'Calcul'!$R$2:$R$85)-MAX(0,SUMIF('Calcul'!$B$2:$B$85,4,'Calcul'!$R$2:$R$85))*'Hypothèses'!$C$54)))) | H7: =MIN('Hypothèses'!$C$56*(SUMIF('Calcul'!$B$2:$B$85,6,'Calcul'!$R$2:$R$85)-MAX(0,SUMIF('Calcul'!$B$2:$B$85,6,'Calcul'!$R$2:$R$85))*'Hypothèses'!$C$54),MAX(0,'Hypothèses'!$C$58-('Hypothèses'!$C$56*(SUMIF('Calcul'!$B$2:$B$85,1,'Calcul'!$R$2:$R$85)-MAX(0,SUMIF('Calcul'!$B$2:$B$85,1,'Calcul'!$R$2:$R$85))*'Hypothèses'!$C$54)+'Hypothèses'!$C$56*(SUMIF('Calcul'!$B$2:$B$85,2,'Calcul'!$R$2:$R$85)-MAX(0,SUMIF('Calcul'!$B$2:$B$85,2,'Calcul'!$R$2:$R$85))*'Hypothèses'!$C$54)+'Hypothèses'!$C$56*(SUMIF('Calcul'!$B$2:$B$85,3,'Calcul'!$R$2:$R$85)-MAX(0,SUMIF('Calcul'!$B$2:$B$85,3,'Calcul'!$R$2:$R$85))*'Hypothèses'!$C$54)+'Hypothèses'!$C$56*(SUMIF('Calcul'!$B$2:$B$85,4,'Calcul'!$R$2:$R$85)-MAX(0,SUMIF('Calcul'!$B$2:$B$85,4,'Calcul'!$R$2:$R$85))*'Hypothèses'!$C$54)+'Hypothèses'!$C$56*(SUMIF('Calcul'!$B$2:$B$85,5,'Calcul'!$R$2:$R$85)-MAX(0,SUMIF('Calcul'!$B$2:$B$85,5,'Calcul'!$R$2:$R$85))*'Hypothèses'!$C$54)))) | I7: =MIN('Hypothèses'!$C$56*(SUMIF('Calcul'!$B$2:$B$85,7,'Calcul'!$R$2:$R$85)-MAX(0,SUMIF('Calcul'!$B$2:$B$85,7,'Calcul'!$R$2:$R$85))*'Hypothèses'!$C$54),MAX(0,'Hypothèses'!$C$58-('Hypothèses'!$C$56*(SUMIF('Calcul'!$B$2:$B$85,1,'Calcul'!$R$2:$R$85)-MAX(0,SUMIF('Calcul'!$B$2:$B$85,1,'Calcul'!$R$2:$R$85))*'Hypothèses'!$C$54)+'Hypothèses'!$C$56*(SUMIF('Calcul'!$B$2:$B$85,2,'Calcul'!$R$2:$R$85)-MAX(0,SUMIF('Calcul'!$B$2:$B$85,2,'Calcul'!$R$2:$R$85))*'Hypothèses'!$C$54)+'Hypothèses'!$C$56*(SUMIF('Calcul'!$B$2:$B$85,3,'Calcul'!$R$2:$R$85)-MAX(0,SUMIF('Calcul'!$B$2:$B$85,3,'Calcul'!$R$2:$R$85))*'Hypothèses'!$C$54)+'Hypothèses'!$C$56*(SUMIF('Calcul'!$B$2:$B$85,4,'Calcul'!$R$2:$R$85)-MAX(0,SUMIF('Calcul'!$B$2:$B$85,4,'Calcul'!$R$2:$R$85))*'Hypothèses'!$C$54)+'Hypothèses'!$C$56*(SUMIF('Calcul'!$B$2:$B$85,5,'Calcul'!$R$2:$R$85)-MAX(0,SUMIF('Calcul'!$B$2:$B$85,5,'Calcul'!$R$2:$R$85))*'Hypothèses'!$C$54)+'Hypothèses'!$C$56*(SUMIF('Calcul'!$B$2:$B$85,6,'Calcul'!$R$2:$R$85)-MAX(0,SUMIF('Calcul'!$B$2:$B$85,6,'Calcul'!$R$2:$R$85))*'Hypothèses'!$C$54)))) | J7: =SUM(C7:I7)
B8: Reste à répartir au pro-rata | C8: ='Hypothèses'!$C$56*(SUMIF('Calcul'!$B$2:$B$85,1,'Calcul'!$R$2:$R$85)-MAX(0,SUMIF('Calcul'!$B$2:$B$85,1,'Calcul'!$R$2:$R$85))*'Hypothèses'!$C$54)-C7 | D8: ='Hypothèses'!$C$56*(SUMIF('Calcul'!$B$2:$B$85,2,'Calcul'!$R$2:$R$85)-MAX(0,SUMIF('Calcul'!$B$2:$B$85,2,'Calcul'!$R$2:$R$85))*'Hypothèses'!$C$54)-D7 | E8: ='Hypothèses'!$C$56*(SUMIF('Calcul'!$B$2:$B$85,3,'Calcul'!$R$2:$R$85)-MAX(0,SUMIF('Calcul'!$B$2:$B$85,3,'Calcul'!$R$2:$R$85))*'Hypothèses'!$C$54)-E7 | F8: ='Hypothèses'!$C$56*(SUMIF('Calcul'!$B$2:$B$85,4,'Calcul'!$R$2:$R$85)-MAX(0,SUMIF('Calcul'!$B$2:$B$85,4,'Calcul'!$R$2:$R$85))*'Hypothèses'!$C$54)-F7 | G8: ='Hypothèses'!$C$56*(SUMIF('Calcul'!$B$2:$B$85,5,'Calcul'!$R$2:$R$85)-MAX(0,SUMIF('Calcul'!$B$2:$B$85,5,'Calcul'!$R$2:$R$85))*'Hypothèses'!$C$54)-G7 | H8: ='Hypothèses'!$C$56*(SUMIF('Calcul'!$B$2:$B$85,6,'Calcul'!$R$2:$R$85)-MAX(0,SUMIF('Calcul'!$B$2:$B$85,6,'Calcul'!$R$2:$R$85))*'Hypothèses'!$C$54)-H7 | I8: ='Hypothèses'!$C$56*(SUMIF('Calcul'!$B$2:$B$85,7,'Calcul'!$R$2:$R$85)-MAX(0,SUMIF('Calcul'!$B$2:$B$85,7,'Calcul'!$R$2:$R$85))*'Hypothèses'!$C$54)-I7 | J8: =SUM(C8:I8)
B9: DIVIDENDES PAR ASSOCIÉ (mêmes colonnes An 1 … An 7)
B11: Nessim Mami (45 %) | C11: =C7+C8*'Hypothèses'!$C$61 | D11: =D7+D8*'Hypothèses'!$C$61 | E11: =E7+E8*'Hypothèses'!$C$61 | F11: =F7+F8*'Hypothèses'!$C$61 | G11: =G7+G8*'Hypothèses'!$C$61 | H11: =H7+H8*'Hypothèses'!$C$61 | I11: =I7+I8*'Hypothèses'!$C$61 | J11: =SUM(C11:I11)
B12: Ali Ben Hamoud (25 %) | C12: =C8*'Hypothèses'!$C$62 | D12: =D8*'Hypothèses'!$C$62 | E12: =E8*'Hypothèses'!$C$62 | F12: =F8*'Hypothèses'!$C$62 | G12: =G8*'Hypothèses'!$C$62 | H12: =H8*'Hypothèses'!$C$62 | I12: =I8*'Hypothèses'!$C$62 | J12: =SUM(C12:I12)
B13: Mohamed Lamine Belajouza (25 %) | C13: =C8*'Hypothèses'!$C$63 | D13: =D8*'Hypothèses'!$C$63 | E13: =E8*'Hypothèses'!$C$63 | F13: =F8*'Hypothèses'!$C$63 | G13: =G8*'Hypothèses'!$C$63 | H13: =H8*'Hypothèses'!$C$63 | I13: =I8*'Hypothèses'!$C$63 | J13: =SUM(C13:I13)
B14: Nazeh Ben Ammar (5 %) | C14: =C8*'Hypothèses'!$C$64 | D14: =D8*'Hypothèses'!$C$64 | E14: =E8*'Hypothèses'!$C$64 | F14: =F8*'Hypothèses'!$C$64 | G14: =G8*'Hypothèses'!$C$64 | H14: =H8*'Hypothèses'!$C$64 | I14: =I8*'Hypothèses'!$C$64 | J14: =SUM(C14:I14)
B15: TOTAL distribué | C15: =SUM(C11:C14) | D15: =SUM(D11:D14) | E15: =SUM(E11:E14) | F15: =SUM(F11:F14) | G15: =SUM(G11:G14) | H15: =SUM(H11:H14) | I15: =SUM(I11:I14) | J15: =SUM(C15:I15)
B17: Multiple Nessim (reçu / capital) | C17: =J11/'Hypothèses'!$C$55
B18: TRI de l'investisseur (Nessim) | C18: =IRR(C20:J20)
B20: Flux investisseur (pour TRI) | C20: =-'Hypothèses'!$C$55 | D20: =C11 | E20: =D11 | F20: =E11 | G20: =F11 | H20: =G11 | I20: =H11 | J20: =I11

Sheet Notes
B1: Notes aux états financiers prévisionnels
B2: Règles de présentation et hypothèses structurantes.
B4: 1. Référentiel comptable
B5: États financiers prévisionnels établis selon le Système Comptable des Entreprises (Tunisie), sur un horizon de 7 ans, exprimés en dinars tunisiens (DT).
B7: 2. Traitement du leasing
B8: Les machines et le véhicule utilitaire sont financés en leasing. Traités en location simple : ils ne figurent pas à l'actif et les loyers sont comptabilisés en charges d'exploitation. Durée du leasing machine : 5 ans (au-delà, loyer nul).
B10: 3. Absence de dette bancaire
B11: Le financement repose exclusivement sur le leasing et le capital social. Aucun emprunt bancaire — d'où des charges financières nulles.
B13: 4. Reconnaissance des revenus
B14: Modèle de revenue share 60/40 : HCTECH perçoit 60 % de la valeur de l'essence récupérée, la station 40 % (sans investissement). Revenus reconnus au rythme de la récupération.
B16: 5. Impôt sur les bénéfices
B17: IS 25 % + CSS 3 % = 28 % du résultat. L'impôt d'un exercice est exigible l'exercice suivant : il figure en passif courant au bilan et son décaissement apparaît l'année N+1 dans les flux.
... B26: Tous les montants découlent par formules de l'onglet « Hypothèses ». Modifier une hypothèse recalcule automatiquement l'ensemble des états financiers.

Sheet Synthèse
B1: Synthèse — indicateurs clés
B2: Vue d'ensemble du dossier de financement leasing.
B4: EXPLOITATION | E4: ACTIONNARIAT & RETOURS
B5: Parc de machines (An 7) | C5: ='Calcul'!$D$85 | E5: Capital social | F5: ='Hypothèses'!$C$55
B6: Chiffre d'affaires HCTECH (An 7) | C6: ='État de résultat'!I7 | E6: Total distribué (7 ans) | F6: =Dividendes!J15
B7: EBITDA (An 7) | C7: ='Ratios financiers'!I8 | E7: Dividendes Nessim (7 ans) | F7: =Dividendes!J11
B8: Marge d'EBITDA (An 7) | C8: ='Ratios financiers'!I13 | E8: Multiple Nessim | F8: =Dividendes!C17
B9: Résultat net (An 7) | C9: ='État de résultat'!I20 | E9: TRI investisseur (Nessim) | F9: =Dividendes!C18
B10: Résultat net cumulé (7 ans) | C10: ='État de résultat'!J20
B11: Trésorerie minimale (84 mois) | C11: ='Flux de trésorerie'!C20
B12: ATTRACTIVITÉ POUR LE BAILLEUR | E12: RÉPARTITION DU CAPITAL
B13: Couverture du loyer / machine | C13: ='Capacité leasing'!C7 | E13: Nessim Mami (investisseur) | F13: ='Hypothèses'!$C$61
B14: DSCR minimum (société) | C14: ='Capacité leasing'!C17 | E14: Ali Ben Hamoud (DT) | F14: ='Hypothèses'!$C$62
B15: Total engagements leasing (7 ans) | C15: ='Capacité leasing'!J13 | E15: Mohamed Lamine Belajouza (CEO) | F15: ='Hypothèses'!$C$63
B16: Dette bancaire | C16: =0 | E16: Nazeh Ben Ammar (conseiller) | F16: ='Hypothèses'!$C$64

Sheet Calcul
A1: Mois | B1: Année | C1: Vagues cum. | D1: Parc | E1: Vagues>durée | F1: Mach. en leasing | G1: Prix essence | H1: Revenu HCTECH | I1: OPEX mach. | J1: Loyer leasing mach. | K1: Nb tech. | L1: Sal. fond. | M1: Sal. tech. | N1: Masse sal. | O1: Loyer bureau | P1: Frais gén. | Q1: Leasing véh. | R1: EBITDA mensuel | S1: Impôt payé | T1: Trésorerie cum.
A2: 1 | B2: =INT((A2-1)/12)+1 | C2: =IF(A2<'Hypothèses'!$C$28,0,MIN('Hypothèses'!$C$29,INT((A2-'Hypothèses'!$C$28)/'Hypothèses'!$C$27)+1)) | D2: =C2*'Hypothèses'!$C$26 | E2: =IF((A2-'Hypothèses'!$C$11*12)<'Hypothèses'!$C$28,0,MIN('Hypothèses'!$C$29,INT((A2-'Hypothèses'!$C$11*12-'Hypothèses'!$C$28)/'Hypothèses'!$C$27)+1)) | F2: =(C2-E2)*'Hypothèses'!$C$26 | G2: ='Hypothèses'!$C$20*(1+'Hypothèses'!$C$21)^(B2-1) | H2: =D2*'Hypothèses'!$C$19*(365/12)*G2*'Hypothèses'!$C$22 | I2: =D2*'Hypothèses'!$C$14 | J2: =F2*'Hypothèses'!$C$12 | K2: =MAX(1,ROUNDUP(D2/'Hypothèses'!$C$40,0)) | L2: =MIN('Hypothèses'!$C$35*(1+'Hypothèses'!$C$36)^(B2-1),'Hypothèses'!$C$37) | M2: ='Hypothèses'!$C$38*(1+'Hypothèses'!$C$39)^(B2-1) | N2: =('Hypothèses'!$C$34*L2+K2*M2)*(1+'Hypothèses'!$C$41) | O2: ='Hypothèses'!$C$42*(1+'Hypothèses'!$C$43)^(B2-1) | P2: ='Hypothèses'!$C$44*(1+'Hypothèses'!$C$45)^(B2-1) | Q2: =IF(A2<='Hypothèses'!$C$50,'Hypothèses'!$C$51,0) | R2: =H2-I2-J2-N2-O2-P2-Q2 | S2: =IF(AND(MOD(A2,12)=6,A2>=18),MAX(0,SUMIF($B$2:$B$85,B2-1,$R$2:$R$85))*'Hypothèses'!$C$54,0) | T2: ='Hypothèses'!$C$55+R2-S2
A3: 2 | B3: =INT((A3-1)/12)+1 | C3: =IF(A3<'Hypothèses'!$C$28,0,MIN('Hypothèses'!$C$29,INT((A3-'Hypothèses'!$C$28)/'Hypothèses'!$C$27)+1)) | D3: =C3*'Hypothèses'!$C$26 | E3: =IF((A3-'Hypothèses'!$C$11*12)<'Hypothèses'!$C$28,0,MIN('Hypothèses'!$C$29,INT((A3-'Hypothèses'!$C$11*12-'Hypothèses'!$C$28)/'Hypothèses'!$C$27)+1)) | F3: =(C3-E3)*'Hypothèses'!$C$26 | G3: ='Hypothèses'!$C$20*(1+'Hypothèses'!$C$21)^(B3-1) | H3: =D3*'Hypothèses'!$C$19*(365/12)*G3*'Hypothèses'!$C$22 | I3: =D3*'Hypothèses'!$C$14 | J3: =F3*'Hypothèses'!$C$12 | K3: =MAX(1,ROUNDUP(D3/'Hypothèses'!$C$40,0)) | L3: =MIN('Hypothèses'!$C$35*(1+'Hypothèses'!$C$36)^(B3-1),'Hypothèses'!$C$37) | M3: ='Hypothèses'!$C$38*(1+'Hypothèses'!$C$39)^(B3-1) | N3: =('Hypothèses'!$C$34*L3+K3*M3)*(1+'Hypothèses'!$C$41) | O3: ='Hypothèses'!$C$42*(1+'Hypothèses'!$C$43)^(B3-1) | P3: ='Hypothèses'!$C$44*(1+'Hypothèses'!$C$45)^(B3-1) | Q3: =IF(A3<='Hypothèses'!$C$50,'Hypothèses'!$C$51,0) | R3: =H3-I3-J3-N3-O3-P3-Q3 | S3: =IF(AND(MOD(A3,12)=6,A3>=18),MAX(0,SUMIF($B$2:$B$85,B3-1,$R$2:$R$85))*'Hypothèses'!$C$54,0) | T3: =T2+R3-S3
A4: 3 | B4: =INT((A4-1)/12)+1 | C4: =IF(A4<'Hypothèses'!$C$28,0,MIN('Hypothèses'!$C$29,INT((A4-'Hypothèses'!$C$28)/'Hypothèses'!$C$27)+1)) | D4: =C4*'Hypothèses'!$C$26 | E4: =IF((A4-'Hypothèses'!$C$11*12)<'Hypothèses'!$C$28,0,MIN('Hypothèses'!$C$29,INT((A4-'Hypothèses'!$C$11*12-'Hypothèses'!$C$28)/'Hypothèses'!$C$27)+1)) | F4: =(C4-E4)*'Hypothèses'!$C$26 | G4: ='Hypothèses'!$C$20*(1+'Hypothèses'!$C$21)^(B4-1) | H4: =D4*'Hypothèses'!$C$19*(365/12)*G4*'Hypothèses'!$C$22 | I4: =D4*'Hypothèses'!$C$14 | J4: =F4*'Hypothèses'!$C$12 | K4: =MAX(1,ROUNDUP(D4/'Hypothèses'!$C$40,0)) | L4: =MIN('Hypothèses'!$C$35*(1+'Hypothèses'!$C$36)^(B4-1),'Hypothèses'!$C$37) | M4: ='Hypothèses'!$C$38*(1+'Hypothèses'!$C$39)^(B4-1) | N4: =('Hypothèses'!$C$34*L4+K4*M4)*(1+'Hypothèses'!$C$41) | O4: ='Hypothèses'!$C$42*(1+'Hypothèses'!$C$43)^(B4-1) | P4: ='Hypothèses'!$C$44*(1+'Hypothèses'!$C$45)^(B4-1) | Q4: =IF(A4<='Hypothèses'!$C$50,'Hypothèses'!$C$51,0) | R4: =H4-I4-J4-N4-O4-P4-Q4 | S4: =IF(AND(MOD(A4,12)=6,A4>=18),MAX(0,SUMIF($B$2:$B$85,B4-1,$R$2:$R$85))*'Hypothèses'!$C$54,0) | T4: =T3+R4-S4
A5: 4 | B5: =INT((A5-1)/12)+1 | C5: =IF(A5<'Hypothèses'!$C$28,0,MIN('Hypothèses'!$C$29,INT((A5-'Hypothèses'!$C$28)/'Hypothèses'!$C$27)+1)) | D5: =C5*'Hypothèses'!$C$26 | E5: =IF((A5-'Hypothèses'!$C$11*12)<'Hypothèses'!$C$28,0,MIN('Hypothèses'!$C$29,INT((A5-'Hypothèses'!$C$11*12-'Hypothèses'!$C$28)/'Hypothèses'!$C$27)+1)) | F5: =(C5-E5)*'Hypothèses'!$C$26 | G5: ='Hypothèses'!$C$20*(1+'Hypothèses'!$C$21)^(B5-1) | H5: =D5*'Hypothèses'!$C$19*(365/12)*G5*'Hypothèses'!$C$22 | I5: =D5*'Hypothèses'!$C$14 | J5: =F5*'Hypothèses'!$C$12 | K5: =MAX(1,ROUNDUP(D5/'Hypothèses'!$C$40,0)) | L5: =MIN('Hypothèses'!$C$35*(1+'Hypothèses'!$C$36)^(B5-1),'Hypothèses'!$C$37) | M5: ='Hypothèses'!$C$38*(1+'Hypothèses'!$C$39)^(B5-1) | N5: =('Hypothèses'!$C$34*L5+K5*M5)*(1+'Hypothèses'!$C$41) | O5: ='Hypothèses'!$C$42*(1+'Hypothèses'!$C$43)^(B5-1) | P5: ='Hypothèses'!$C$44*(1+'Hypothèses'!$C$45)^(B5-1) | Q5: =IF(A5<='Hypothèses'!$C$50,'Hypothèses'!$C$51,0) | R5: =H5-I5-J5-N5-O5-P5-Q5 | S5: =IF(AND(MOD(A5,12)=6,A5>=18),MAX(0,SUMIF($B$2:$B$85,B5-1,$R$2:$R$85))*'Hypothèses'!$C$54,0) | T5: =T4+R5-S5
A6: 5 | B6: =INT((A6-1)/12)+1 | C6: =IF(A6<'Hypothèses'!$C$28,0,MIN('Hypothèses'!$C$29,INT((A6-'Hypothèses'!$C$28)/'Hypothèses'!$C$27)+1)) | D6: =C6*'Hypothèses'!$C$26 | E6: =IF((A6-'Hypothèses'!$C$11*12)<'Hypothèses'!$C$28,0,MIN('Hypothèses'!$C$29,INT((A6-'Hypothèses'!$C$11*12-'Hypothèses'!$C$28)/'Hypothèses'!$C$27)+1)) | F6: =(C6-E6)*'Hypothèses'!$C$26 | G6: ='Hypothèses'!$C$20*(1+'Hypothèses'!$C$21)^(B6-1) | H6: =D6*'Hypothèses'!$C$19*(365/12)*G6*'Hypothèses'!$C$22 | I6: =D6*'Hypothèses'!$C$14 | J6: =F6*'Hypothèses'!$C$12 | K6: =MAX(1,ROUNDUP(D6/'Hypothèses'!$C$40,0)) | L6: =MIN('Hypothèses'!$C$35*(1+'Hypothèses'!$C$36)^(B6-1),'Hypothèses'!$C$37) | M6: ='Hypothèses'!$C$38*(1+'Hypothèses'!$C$39)^(B6-1) | N6: =('Hypothèses'!$C$34*L6+K6*M6)*(1+'Hypothèses'!$C$41) | O6: ='Hypothèses'!$C$42*(1+'Hypothèses'!$C$43)^(B6-1) | P6: ='Hypothèses'!$C$44*(1+'Hypothèses'!$C$45)^(B6-1) | Q6: =IF(A6<='Hypothèses'!$C$50,'Hypothèses'!$C$51,0) | R6: =H6-I6-J6-N6-O6-P6-Q6 | S6: =IF(AND(MOD(A6,12)=6,A6>=18),MAX(0,SUMIF($B$2:$B$85,B6-1,$R$2:$R$85))*'Hypothèses'!$C$54,0) | T6: =T5+R6-S6
A7: 6 | B7: =INT((A7-1)/12)+1 | C7: =IF(A7<'Hypothèses'!$C$28,0,MIN('Hypothèses'!$C$29,INT((A7-'Hypothèses'!$C$28)/'Hypothèses'!$C$27)+1)) | D7: =C7*'Hypothèses'!$C$26 | E7: =IF((A7-'Hypothèses'!$C$11*12)<'Hypothèses'!$C$28,0,MIN('Hypothèses'!$C$29,INT((A7-'Hypothèses'!$C$11*12-'Hypothèses'!$C$28)/'Hypothèses'!$C$27)+1)) | F7: =(C7-E7)*'Hypothèses'!$C$26 | G7: ='Hypothèses'!$C$20*(1+'Hypothèses'!$C$21)^(B7-1) | H7: =D7*'Hypothèses'!$C$19*(365/12)*G7*'Hypothèses'!$C$22 | I7: =D7*'Hypothèses'!$C$14 | J7: =F7*'Hypothèses'!$C$12 | K7: =MAX(1,ROUNDUP(D7/'Hypothèses'!$C$40,0)) | L7: =MIN('Hypothèses'!$C$35*(1+'Hypothèses'!$C$36)^(B7-1),'Hypothèses'!$C$37) | M7: ='Hypothèses'!$C$38*(1+'Hypothèses'!$C$39)^(B7-1) | N7: =('Hypothèses'!$C$34*L7+K7*M7)*(1+'Hypothèses'!$C$41) | O7: ='Hypothèses'!$C$42*(1+'Hypothèses'!$C$43)^(B7-1) | P7: ='Hypothèses'!$C$44*(1+'Hypothèses'!$C$45)^(B7-1) | Q7: =IF(A7<='Hypothèses'!$C$50,'Hypothèses'!$C$51,0) | R7: =H7-I7-J7-N7-O7-P7-Q7 | S7: =IF(AND(MOD(A7,12)=6,A7>=18),MAX(0,SUMIF($B$2:$B$85,B7-1,$R$2:$R$85))*'Hypothèses'!$C$54,0) | T7: =T6+R7-S7
A8: 7 | B8: =INT((A8-1)/12)+1 | C8: =IF(A8<'Hypothèses'!$C$28,0,MIN('Hypothèses'!$C$29,INT((A8-'Hypothèses'!$C$28)/'Hypothèses'!$C$27)+1)) | D8: =C8*'Hypothèses'!$C$26 | E8: =IF((A8-'Hypothèses'!$C$11*12)<'Hypothèses'!$C$28,0,MIN('Hypothèses'!$C$29,INT((A8-'Hypothèses'!$C$11*12-'Hypothèses'!$C$28)/'Hypothèses'!$C$27)+1)) | F8: =(C8-E8)*'Hypothèses'!$C$26 | G8: ='Hypothèses'!$C$20*(1+'Hypothèses'!$C$21)^(B8-1) | H8: =D8*'Hypothèses'!$C$19*(365/12)*G8*'Hypothèses'!$C$22 | I8: =D8*'Hypothèses'!$C$14 | J8: =F8*'Hypothèses'!$C$12 | K8: =MAX(1,ROUNDUP(D8/'Hypothèses'!$C$40,0)) | L8: =MIN('Hypothèses'!$C$35*(1+'Hypothèses'!$C$36)^(B8-1),'Hypothèses'!$C$37) | M8: ='Hypothèses'!$C$38*(1+'Hypothèses'!$C$39)^(B8-1) | N8: =('Hypothèses'!$C$34*L8+K8*M8)*(1+'Hypothèses'!$C$41) | O8: ='Hypothèses'!$C$42*(1+'Hypothèses'!$C$43)^(B8-1) | P8: ='Hypothèses'!$C$44*(1+'Hypothèses'!$C$45)^(B8-1) | Q8: =IF(A8<='Hypothèses'!$C$50,'Hypothèses'!$C$51,0) | R8: =H8-I8-J8-N8-O8-P8-Q8 | S8: =IF(AND(MOD(A8,12)=6,A8>=18),MAX(0,SUMIF($B$2:$B$85,B8-1,$R$2:$R$85))*'Hypothèses'!$C$54,0) | T8: =T7+R8-S8
A9: 8 | B9: =INT((A9-1)/12)+1 | C9: =IF(A9<'Hypothèses'!$C$28,0,MIN('Hypothèses'!$C$29,INT((A9-'Hypothèses'!$C$28)/'Hypothèses'!$C$27)+1)) | D9: =C9*'Hypothèses'!$C$26 | E9: =IF((A9-'Hypothèses'!$C$11*12)<'Hypothèses'!$C$28,0,MIN('Hypothèses'!$C$29,INT((A9-'Hypothèses'!$C$11*12-'Hypothèses'!$C$28)/'Hypothèses'!$C$27)+1)) | F9: =(C9-E9)*'Hypothèses'!$C$26 | G9: ='Hypothèses'!$C$20*(1+'Hypothèses'!$C$21)^(B9-1) | H9: =D9*'Hypothèses'!$C$19*(365/12)*G9*'Hypothèses'!$C$22 | I9: =D9*'Hypothèses'!$C$14 | J9: =F9*'Hypothèses'!$C$12 | K9: =MAX(1,ROUNDUP(D9/'Hypothèses'!$C$40,0)) | L9: =MIN('Hypothèses'!$C$35*(1+'Hypothèses'!$C$36)^(B9-1),'Hypothèses'!$C$37) | M9: ='Hypothèses'!$C$38*(1+'Hypothèses'!$C$39)^(B9-1) | N9: =('Hypothèses'!$C$34*L9+K9*M9)*(1+'Hypothèses'!$C$41) | O9: ='Hypothèses'!$C$42*(1+'Hypothèses'!$C$43)^(B9-1) | P9: ='Hypothèses'!$C$44*(1+'Hypothèses'!$C$45)^(B9-1) | Q9: =IF(A9<='Hypothèses'!$C$50,'Hypothèses'!$C$51,0) | R9: =H9-I9-J9-N9-O9-P9-Q9 | S9: =IF(AND(MOD(A9,12)=6,A9>=18),MAX(0,SUMIF($B$2:$B$85,B9-1,$R$2:$R$85))*'Hypothèses'!$C$54,0) | T9: =T8+R9-S9
A10: 9 | B10: =INT((A10-1)/12)+1 | C10: =IF(A10<'Hypothèses'!$C$28,0,MIN('Hypothèses'!$C$29,INT((A10-'Hypothèses'!$C$28)/'Hypothèses'!$C$27)+1)) | D10: =C10*'Hypothèses'!$C$26 | E10: =IF((A10-'Hypothèses'!$C$11*12)<'Hypothèses'!$C$28,0,MIN('Hypothèses'!$C$29,INT((A10-'Hypothèses'!$C$11*12-'Hypothèses'!$C$28)/'Hypothèses'!$C$27)+1)) | F10: =(C10-E10)*'Hypothèses'!$C$26 | G10: ='Hypothèses'!$C$20*(1+'Hypothèses'!$C$21)^(B10-1) | H10: =D10*'Hypothèses'!$C$19*(365/12)*G10*'Hypothèses'!$C$22 | I10: =D10*'Hypothèses'!$C$14 | J10: =F10*'Hypothèses'!$C$12 | K10: =MAX(1,ROUNDUP(D10/'Hypothèses'!$C$40,0)) | L10: =MIN('Hypothèses'!$C$35*(1+'Hypothèses'!$C$36)^(B10-1),'Hypothèses'!$C$37) | M10: ='Hypothèses'!$C$38*(1+'Hypothèses'!$C$39)^(B10-1) | N10: =('Hypothèses'!$C$34*L10+K10*M10)*(1+'Hypothèses'!$C$41) | O10: ='Hypothèses'!$C$42*(1+'Hypothèses'!$C$43)^(B10-1) | P10: ='Hypothèses'!$C$44*(1+'Hypothèses'!$C$45)^(B10-1) | Q10: =IF(A10<='Hypothèses'!$C$50,'Hypothèses'!$C$51,0) | R10: =H10-I10-J10-N10-O10-P10-Q10 | S10: =IF(AND(MOD(A10,12)=6,A10>=18),MAX(0,SUMIF($B$2:$B$85,B10-1,$R$2:$R$85))*'Hypothèses'!$C$54,0) | T10: =T9+R10-S10
A11: 10 | B11: =INT((A11-1)/12)+1 | C11: =IF(A11<'Hypothèses'!$C$28,0,MIN('Hypothèses'!$C$29,INT((A11-'Hypothèses'!$C$28)/'Hypothèses'!$C$27)+1)) | D11: =C11*'Hypothèses'!$C$26 | E11: =IF((A11-'Hypothèses'!$C$11*12)<'Hypothèses'!$C$28,0,MIN('Hypothèses'!$C$29,INT((A11-'Hypothèses'!$C$11*12-'Hypothèses'!$C$28)/'Hypothèses'!$C$27)+1)) | F11: =(C11-E11)*'Hypothèses'!$C$26 | G11: ='Hypothèses'!$C$20*(1+'Hypothèses'!$C$21)^(B11-1) | H11: =D11*'Hypothèses'!$C$19*(365/12)*G11*'Hypothèses'!$C$22 | I11: =D11*'Hypothèses'!$C$14 | J11: =F11*'Hypothèses'!$C$12 | K11: =MAX(1,ROUNDUP(D11/'Hypothèses'!$C$40,0)) | L11: =MIN('Hypothèses'!$C$35*(1+'Hypothèses'!$C$36)^(B11-1),'Hypothèses'!$C$37) | M11: ='Hypothèses'!$C$38*(1+'Hypothèses'!$C$39)^(B11-1) | N11: =('Hypothèses'!$C$34*L11+K11*M11)*(1+'Hypothèses'!$C$41) | O11: ='Hypothèses'!$C$42*(1+'Hypothèses'!$C$43)^(B11-1) | P11: ='Hypothèses'!$C$44*(1+'Hypothèses'!$C$45)^(B11-1) | Q11: =IF(A11<='Hypothèses'!$C$50,'Hypothèses'!$C$51,0) | R11: =H11-I11-J11-N11-O11-P11-Q11 | S11: =IF(AND(MOD(A11,12)=6,A11>=18),MAX(0,SUMIF($B$2:$B$85,B11-1,$R$2:$R$85))*'Hypothèses'!$C$54,0) | T11: =T10+R11-S11
A12: 11 | B12: =INT((A12-1)/12)+1 | C12: =IF(A12<'Hypothèses'!$C$28,0,MIN('Hypothèses'!$C$29,INT((A12-'Hypothèses'!$C$28)/'Hypothèses'!$C$27)+1)) | D12: =C12*'Hypothèses'!$C$26 | E12: =IF((A12-'Hypothèses'!$C$11*12)<'Hypothèses'!$C$28,0,MIN('Hypothèses'!$C$29,INT((A12-'Hypothèses'!$C$11*12-'Hypothèses'!$C$28)/'Hypothèses'!$C$27)+1)) | F12: =(C12-E12)*'Hypothèses'!$C$26 | G12: ='Hypothèses'!$C$20*(1+'Hypothèses'!$C$21)^(B12-1) | H12: =D12*'Hypothèses'!$C$19*(365/12)*G12*'Hypothèses'!$C$22 | I12: =D12*'Hypothèses'!$C$14 | J12: =F12*'Hypothèses'!$C$12 | K12: =MAX(1,ROUNDUP(D12/'Hypothèses'!$C$40,0)) | L12: =MIN('Hypothèses'!$C$35*(1+'Hypothèses'!$C$36)^(B12-1),'Hypothèses'!$C$37) | M12: ='Hypothèses'!$C$38*(1+'Hypothèses'!$C$39)^(B12-1) | N12: =('Hypothèses'!$C$34*L12+K12*M12)*(1+'Hypothèses'!$C$41) | O12: ='Hypothèses'!$C$42*(1+'Hypothèses'!$C$43)^(B12-1) | P12: ='Hypothèses'!$C$44*(1+'Hypothèses'!$C$45)^(B12-1) | Q12: =IF(A12<='Hypothèses'!$C$50,'Hypothèses'!$C$51,0) | R12: =H12-I12-J12-N12-O12-P12-Q12 | S12: =IF(AND(MOD(A12,12)=6,A12>=18),MAX(0,SUMIF($B$2:$B$85,B12-1,$R$2:$R$85))*'Hypothèses'!$C$54,0) | T12: =T11+R12-S12
A13: 12 | B13: =INT((A13-1)/12)+1 | C13: =IF(A13<'Hypothèses'!$C$28,0,MIN('Hypothèses'!$C$29,INT((A13-'Hypothèses'!$C$28)/'Hypothèses'!$C$27)+1)) | D13: =C13*'Hypothèses'!$C$26 | E13: =IF((A13-'Hypothèses'!$C$11*12)<'Hypothèses'!$C$28,0,MIN('Hypothèses'!$C$29,INT((A13-'Hypothèses'!$C$11*12-'Hypothèses'!$C$28)/'Hypothèses'!$C$27)+1)) | F13: =(C13-E13)*'Hypothèses'!$C$26 | G13: ='Hypothèses'!$C$20*(1+'Hypothèses'!$C$21)^(B13-1) | H13: =D13*'Hypothèses'!$C$19*(365/12)*G13*'Hypothèses'!$C$22 | I13: =D13*'Hypothèses'!$C$14 | J13: =F13*'Hypothèses'!$C$12 | K13: =MAX(1,ROUNDUP(D13/'Hypothèses'!$C$40,0)) | L13: =MIN('Hypothèses'!$C$35*(1+'Hypothèses'!$C$36)^(B13-1),'Hypothèses'!$C$37) | M13: ='Hypothèses'!$C$38*(1+'Hypothèses'!$C$39)^(B13-1) | N13: =('Hypothèses'!$C$34*L13+K13*M13)*(1+'Hypothèses'!$C$41) | O13: ='Hypothèses'!$C$42*(1+'Hypothèses'!$C$43)^(B13-1) | P13: ='Hypothèses'!$C$44*(1+'Hypothèses'!$C$45)^(B13-1) | Q13: =IF(A13<='Hypothèses'!$C$50,'Hypothèses'!$C$51,0) | R13: =H13-I13-J13-N13-O13-P13-Q13 | S13: =IF(AND(MOD(A13,12)=6,A13>=18),MAX(0,SUMIF($B$2:$B$85,B13-1,$R$2:$R$85))*'Hypothèses'!$C$54,0) | T13: =T12+R13-S13
A14: 13 | B14: =INT((A14-1)/12)+1 | C14: =IF(A14<'Hypothèses'!$C$28,0,MIN('Hypothèses'!$C$29,INT((A14-'Hypothèses'!$C$28)/'Hypothèses'!$C$27)+1)) | D14: =C14*'Hypothèses'!$C$26 | E14: =IF((A14-'Hypothèses'!$C$11*12)<'Hypothèses'!$C$28,0,MIN('Hypothèses'!$C$29,INT((A14-'Hypothèses'!$C$11*12-'Hypothèses'!$C$28)/'Hypothèses'!$C$27)+1)) | F14: =(C14-E14)*'Hypothèses'!$C$26 | G14: ='Hypothèses'!$C$20*(1+'Hypothèses'!$C$21)^(B14-1) | H14: =D14*'Hypothèses'!$C$19*(365/12)*G14*'Hypothèses'!$C$22 | I14: =D14*'Hypothèses'!$C$14 | J14: =F14*'Hypothèses'!$C$12 | K14: =MAX(1,ROUNDUP(D14/'Hypothèses'!$C$40,0)) | L14: =MIN('Hypothèses'!$C$35*(1+'Hypothèses'!$C$36)^(B14-1),'Hypothèses'!$C$37) | M14: ='Hypothèses'!$C$38*(1+'Hypothèses'!$C$39)^(B14-1) | N14: =('Hypothèses'!$C$34*L14+K14*M14)*(1+'Hypothèses'!$C$41) | O14: ='Hypothèses'!$C$42*(1+'Hypothèses'!$C$43)^(B14-1) | P14: ='Hypothèses'!$C$44*(1+'Hypothèses'!$C$45)^(B14-1) | Q14: =IF(A14<='Hypothèses'!$C$50,'Hypothèses'!$C$51,0) | R14: =H14-I14-J14-N14-O14-P14-Q14 | S14: =IF(AND(MOD(A14,12)=6,A14>=18),MAX(0,SUMIF($B$2:$B$85,B14-1,$R$2:$R$85))*'Hypothèses'!$C$54,0) | T14: =T13+R14-S14
... A85: 84 | B85: =INT((A85-1)/12)+1 | C85: =IF(A85<'Hypothèses'!$C$28,0,MIN('Hypothèses'!$C$29,INT((A85-'Hypothèses'!$C$28)/'Hypothèses'!$C$27)+1)) | D85: =C85*'Hypothèses'!$C$26 | E85: =IF((A85-'Hypothèses'!$C$11*12)<'Hypothèses'!$C$28,0,MIN('Hypothèses'!$C$29,INT((A85-'Hypothèses'!$C$11*12-'Hypothèses'!$C$28)/'Hypothèses'!$C$27)+1)) | F85: =(C85-E85)*'Hypothèses'!$C$26 | G85: ='Hypothèses'!$C$20*(1+'Hypothèses'!$C$21)^(B85-1) | H85: =D85*'Hypothèses'!$C$19*(365/12)*G85*'Hypothèses'!$C$22 | I85: =D85*'Hypothèses'!$C$14 | J85: =F85*'Hypothèses'!$C$12 | K85: =MAX(1,ROUNDUP(D85/'Hypothèses'!$C$40,0)) | L85: =MIN('Hypothèses'!$C$35*(1+'Hypothèses'!$C$36)^(B85-1),'Hypothèses'!$C$37) | M85: ='Hypothèses'!$C$38*(1+'Hypothèses'!$C$39)^(B85-1) | N85: =('Hypothèses'!$C$34*L85+K85*M85)*(1+'Hypothèses'!$C$41) | O85: ='Hypothèses'!$C$42*(1+'Hypothèses'!$C$43)^(B85-1) | P85: ='Hypothèses'!$C$44*(1+'Hypothèses'!$C$45)^(B85-1) | Q85: =IF(A85<='Hypothèses'!$C$50,'Hypothèses'!$C$51,0) | R85: =H85-I85-J85-N85-O85-P85-Q85 | S85: =IF(AND(MOD(A85,12)=6,A85>=18),MAX(0,SUMIF($B$2:$B$85,B85-1,$R$2:$R$85))*'Hypothèses'!$C$54,0) | T85: =T84+R85-S85
